

<page id="I-64-2v" xy="740, 187, 4748, 4874"><col id="I-64-2v-1" xy="1403, 966, 2858, 3922"><line id="I-64-2v-1-1" xy="1403, 966, 2858, 1027"><word id="I-B27K3V13-27-PROV-1" xy="1397, 962, 1790, 1026">μακαριοϲ</word><word id="I-B27K3V13-27-PROV-2" xy="1791, 962, 2225, 1026">ανθρωποϲ</word><word id="I-B27K3V13-27-PROV-3" xy="2220, 964, 2243, 1028">·</word><word id="I-B27K3V13-27-PROV-4" xy="2246, 966, 2337, 1027">οϲ</word><word id="I-B27K3V13-27-PROV-5" xy="2337, 966, 2574, 1027">ευρεν</word><word id="I-B27K3V13-27-PROV-6" xy="2574, 966, 2880, 1027">ϲοφιαν</word></line><line id="I-64-2v-1-2" xy="1403, 1027, 2671, 1091"><word id="I-B27K3V13-27-PROV-7" xy="1386, 1027, 1547, 1094">και</word><word id="I-B27K3V13-27-PROV-8" xy="1555, 1027, 1876, 1094">θνητοϲ</word><word id="I-B27K3V13-27-PROV-9" xy="1863, 1026, 1893, 1093">·</word><word id="I-B27K3V13-27-PROV-10" xy="1898, 1026, 1999, 1093">οϲ</word><word id="I-B27K3V13-27-PROV-11" xy="2002, 1027, 2249, 1094">ειδεν</word><word id="I-B27K3V13-27-PROV-12" xy="2246, 1027, 2692, 1091">φρονηϲιν</word></line><line id="I-64-2v-1-3" xy="1410, 1089, 2736, 1153"><word id="I-B27K3V14-27-PROV-1" xy="1409, 1088, 1756, 1155">κριττον</word><word id="I-B27K3V14-27-PROV-2" xy="1755, 1087, 1892, 1154">γαρ</word><word id="I-B27K3V14-27-PROV-3" xy="1881, 1091, 2137, 1158">αυτην</word><word id="I-B27K3V14-27-PROV-4" xy="2148, 1089, 2718, 1156">εμπορευεϲθαι</word><word id="I-B27K3V14-27-PROV-5" xy="2719, 1089, 2744, 1156">·</word></line><line id="I-64-2v-1-4" xy="1405, 1147, 2752, 1211"><word id="I-B27K3V14-27-PROV-6" xy="1391, 1149, 1482, 1216">η</word><word id="I-B27K3V14-27-PROV-7" xy="1478, 1151, 1803, 1218">χρυϲιου</word><word id="I-B27K3V14-27-PROV-8" xy="1805, 1152, 1936, 1219">και</word><word id="I-B27K3V14-27-PROV-9" xy="1934, 1152, 2284, 1219">αργυριου</word><word id="I-B27K3V14-27-PROV-10" xy="2282, 1152, 2732, 1219">θηϲαυρουϲ</word><word id="I-B27K3V14-27-PROV-11" xy="2730, 1150, 2759, 1217">·</word></line><line id="I-64-2v-1-5" xy="1403, 1212, 2858, 1273"><word id="I-B27K3V15-27-PROV-1" xy="1379, 1213, 1845, 1277">τιμιωτερα</word><word id="I-B27K3V15-27-PROV-2" xy="1845, 1214, 1948, 1278">δε</word><word id="I-B27K3V15-27-PROV-3" xy="1948, 1218, 2190, 1282">εϲτιν</word><word id="I-B27K3V15-27-PROV-4" xy="2185, 1218, 2208, 1282">·</word><word id="I-B27K3V15-27-PROV-5" xy="2202, 1215, 2464, 1279">λιθων</word><word id="I-B27K3V15-27-PROV-6" xy="2463, 1217, 2873, 1281">πολυτελων</word></line><line id="I-64-2v-1-6" xy="1407, 1273, 2847, 1337"><word id="I-B27K3V15-27-PROV-7" xy="1397, 1273, 1581, 1340">ουκ</word><word id="I-B27K3V15-27-PROV-8" xy="1583, 1274, 2084, 1341">αντιταξεται</word><word id="I-B27K3V15-27-PROV-9" xy="2083, 1275, 2280, 1342">αυτη</word><word id="I-B27K3V15-27-PROV-10" xy="2277, 1276, 2304, 1343">·</word><word id="I-B27K3V15-27-PROV-11" xy="2299, 1274, 2565, 1341">ουδεν</word><word id="I-B27K3V15-27-PROV-12" xy="2565, 1277, 2848, 1344">πονηρο</word></line><line id="I-64-2v-1-7" xy="1404, 1336, 2726, 1400"><word id="I-B27K3V15-27-PROV-13" xy="1400, 1336, 1904, 1403">ευγνωϲτοϲ</word><word id="I-B27K3V15-27-PROV-14" xy="1907, 1336, 2126, 1403">εϲτιν</word><word id="I-B27K3V15-27-PROV-15" xy="2119, 1340, 2150, 1407">·</word><word id="I-B27K3V15-27-PROV-16" xy="2136, 1338, 2388, 1405">παϲιν</word><word id="I-B27K3V15-27-PROV-17" xy="2399, 1340, 2571, 1407">τοιϲ</word><word id="I-B27K3V15-27-PROV-18-1" xy="2571, 1344, 2768, 1411">εγγι</word></line><line id="I-64-2v-1-8" xy="1625, 1397, 2168, 1461"><word id="I-B27K3V15-27-PROV-18-2" xy="1623, 1397, 1941, 1464">ζουϲιν</word><word id="I-B27K3V15-27-PROV-19" xy="1942, 1397, 2146, 1464">αυτη</word><word id="I-B27K3V15-27-PROV-20" xy="2148, 1397, 2181, 1464">·</word></line><line id="I-64-2v-1-9" xy="1406, 1459, 2891, 1523"><word id="I-B27K3V15-27-PROV-21" xy="1381, 1459, 1580, 1523">παν</word><word id="I-B27K3V15-27-PROV-22" xy="1580, 1459, 1685, 1523">δε</word><word id="I-B27K3V15-27-PROV-23" xy="1692, 1463, 2013, 1530">τιμιον</word><word id="I-B27K3V15-27-PROV-24" xy="2009, 1462, 2027, 1529">·</word><word id="I-B27K3V15-27-PROV-25" xy="2028, 1463, 2189, 1530">ουκ</word><word id="I-B27K3V15-27-PROV-26" xy="2192, 1462, 2427, 1529">αξιον</word><word id="I-B27K3V15-27-PROV-27" xy="2424, 1462, 2669, 1529">αυτηϲ</word><word id="I-B27K3V15-27-PROV-28" xy="2663, 1460, 2877, 1527">εϲτιν</word><word id="I-B27K3V15-27-PROV-29" xy="2874, 1464, 2904, 1531">·</word></line><line id="I-64-2v-1-10" xy="1400, 1521, 2781, 1585"><word id="I-B27K3V16-27-PROV-1" xy="1399, 1522, 1705, 1589">μηκοϲ</word><word id="I-B27K3V16-27-PROV-2" xy="1701, 1522, 1836, 1589">γαρ</word><word id="I-B27K3V16-27-PROV-3" xy="1842, 1524, 2004, 1591">βιου</word><word id="I-B27K3V16-27-PROV-4" xy="1996, 1526, 2020, 1593">·</word><word id="I-B27K3V16-27-PROV-5" xy="2017, 1521, 2143, 1585">και</word><word id="I-B27K3V16-27-PROV-6" xy="2145, 1521, 2301, 1588">ετη</word><word id="I-B27K3V16-27-PROV-7" xy="2303, 1522, 2547, 1589">ζωηϲ</word><word id="I-B27K3V16-27-PROV-8" xy="2534, 1530, 2567, 1597">·</word><word id="I-B27K3V16-27-PROV-9" xy="2559, 1525, 2668, 1592">εν</word><word id="I-B27K3V16-27-PROV-10" xy="2668, 1527, 2790, 1594">τη</word></line><line id="I-64-2v-1-11" xy="1615, 1584, 2138, 1648"><word id="I-B27K3V16-27-PROV-11" xy="1590, 1584, 1867, 1648">δεξια</word><word id="I-B27K3V16-27-PROV-12" xy="1867, 1584, 2162, 1648">αυτηϲ</word></line><line id="I-64-2v-1-12" xy="1403, 1642, 2713, 1706"><word id="I-B27K3V16-27-PROV-13" xy="1378, 1642, 1515, 1706">εν</word><word id="I-B27K3V16-27-PROV-14" xy="1515, 1642, 1623, 1706">δε</word><word id="I-B27K3V16-27-PROV-15" xy="1623, 1642, 1722, 1706">τη</word><word id="I-B27K3V16-27-PROV-16" xy="1742, 1644, 2085, 1711">αριϲτερα</word><word id="I-B27K3V16-27-PROV-17" xy="2088, 1642, 2338, 1709">αυτηϲ</word><word id="I-B27K3V16-27-PROV-18" xy="2337, 1642, 2362, 1709">·</word><word id="I-B27K3V16-27-PROV-19" xy="2353, 1643, 2731, 1710">πλουτοϲ</word></line><line id="I-64-2v-1-13" xy="1637, 1706, 1993, 1770"><word id="I-B27K3V16-27-PROV-20" xy="1612, 1706, 1775, 1770">και</word><word id="I-B27K3V16-27-PROV-21" xy="1775, 1706, 2017, 1770">δοξα</word></line><line id="I-64-2v-1-14" xy="1405, 1762, 2742, 1826"><word id="I-B27K3V16-27-PROV-22" xy="1380, 1762, 1513, 1826">εκ</word><word id="I-B27K3V16-27-PROV-23" xy="1524, 1762, 1664, 1829">του</word><word id="I-B27K3V16-27-PROV-24" xy="1665, 1761, 2092, 1828">ϲτοματοϲ</word><word id="I-B27K3V16-27-PROV-25" xy="2094, 1760, 2344, 1827">αυτηϲ</word><word id="I-B27K3V16-27-PROV-26" xy="2336, 1763, 2360, 1830">·</word><word id="I-B27K3V16-27-PROV-27-1" xy="2358, 1763, 2769, 1830">εκπορευε</word></line><line id="I-64-2v-1-15" xy="1617, 1825, 2301, 1889"><word id="I-B27K3V16-27-PROV-27-2" xy="1616, 1825, 1758, 1892">ται</word><word id="I-B27K3V16-27-PROV-28" xy="1758, 1825, 2284, 1892">δικαιοϲυνη</word><word id="I-B27K3V16-27-PROV-29" xy="2282, 1825, 2309, 1892">·</word></line><line id="I-64-2v-1-16" xy="1402, 1888, 2915, 1952"><word id="I-B27K3V16-27-PROV-30" xy="1405, 1885, 1727, 1952">νομον</word><word id="I-B27K3V16-27-PROV-31" xy="1740, 1888, 1843, 1955">δε</word><word id="I-B27K3V16-27-PROV-32" xy="1850, 1891, 1977, 1958">και</word><word id="I-B27K3V16-27-PROV-33" xy="1986, 1888, 2235, 1955">ελεον</word><word id="I-B27K3V16-27-PROV-34" xy="2231, 1889, 2259, 1956">·</word><word id="I-B27K3V16-27-PROV-35" xy="2261, 1885, 2396, 1952">επι</word><word id="I-B27K3V16-27-PROV-36" xy="2405, 1891, 2787, 1958">γλωϲϲηϲ</word><word id="I-B27K3V16-27-PROV-37" xy="2788, 1891, 2926, 1958">φορει</word></line><line id="I-64-2v-1-17" xy="1398, 1948, 2441, 2012"><word id="I-B27K3V17-27-PROV-1" xy="1385, 1948, 1489, 2015">αι</word><word id="I-B27K3V17-27-PROV-2" xy="1489, 1948, 1694, 2015">οδοι</word><word id="I-B27K3V17-27-PROV-3" xy="1704, 1949, 1957, 2016">αυτηϲ</word><word id="I-B27K3V17-27-PROV-4" xy="1947, 1949, 1967, 2016">·</word><word id="I-B27K3V17-27-PROV-5" xy="1964, 1948, 2153, 2012">οδοι</word><word id="I-B27K3V17-27-PROV-6" xy="2170, 1949, 2420, 2016">καλαι</word><word id="I-B27K3V17-27-PROV-7" xy="2420, 1950, 2451, 2017">·</word></line><line id="I-64-2v-1-18" xy="1403, 2010, 2847, 2074"><word id="I-B27K3V17-27-PROV-8" xy="1378, 2010, 1551, 2074">και</word><word id="I-B27K3V17-27-PROV-9" xy="1547, 2011, 1906, 2078">παντεϲ</word><word id="I-B27K3V17-27-PROV-10" xy="1915, 2011, 2004, 2078">οι</word><word id="I-B27K3V17-27-PROV-11" xy="2009, 2011, 2277, 2078">τριβοι</word><word id="I-B27K3V17-27-PROV-12" xy="2276, 2010, 2555, 2077">αυτηϲ</word><word id="I-B27K3V17-27-PROV-13" xy="2548, 2010, 2855, 2077">ειρηνη</word></line><line id="I-64-2v-1-19" xy="1388, 2066, 2630, 2130"><word id="I-B27K3V18-27-PROV-1" xy="1379, 2070, 1682, 2137">ξυλον</word><word id="I-B27K3V18-27-PROV-2" xy="1679, 2068, 1949, 2135">ζωηϲ</word><word id="I-B27K3V18-27-PROV-3" xy="1949, 2071, 2130, 2138">εϲτι</word><word id="I-B27K3V18-27-PROV-4" xy="2129, 2070, 2149, 2137">·</word><word id="I-B27K3V18-27-PROV-5" xy="2146, 2066, 2343, 2130">παϲι</word><word id="I-B27K3V18-27-PROV-6" xy="2355, 2066, 2523, 2133">τοιϲ</word><word id="I-B27K3V18-27-PROV-7-1" xy="2515, 2072, 2661, 2139">αν</word></line><line id="I-64-2v-1-20" xy="1602, 2128, 2443, 2192"><word id="I-B27K3V18-27-PROV-7-2" xy="1619, 2129, 2172, 2196">τεχομενοιϲ</word><word id="I-B27K3V18-27-PROV-8" xy="2165, 2132, 2429, 2199">αυτηϲ</word><word id="I-B27K3V18-27-PROV-9" xy="2422, 2131, 2456, 2198">·</word></line><line id="I-64-2v-1-21" xy="1392, 2194, 2781, 2258"><word id="I-B27K3V18-27-PROV-10" xy="1375, 2191, 1543, 2258">και</word><word id="I-B27K3V18-27-PROV-11" xy="1544, 2194, 1717, 2261">τοιϲ</word><word id="I-B27K3V18-27-PROV-12" xy="1723, 2196, 2409, 2263">επεριδομενοιϲ</word><word id="I-B27K3V18-27-PROV-13" xy="2403, 2199, 2529, 2266">επ</word><word id="I-B27K3V18-27-PROV-14" xy="2516, 2198, 2794, 2265">αυτην</word></line><line id="I-64-2v-1-22" xy="1617, 2254, 2316, 2318"><word id="I-B27K3V18-27-PROV-15" xy="1620, 2249, 1763, 2316">ωϲ</word><word id="I-B27K3V18-27-PROV-16" xy="1763, 2254, 1915, 2321">επι</word><word id="I-B27K3V18-27-PROV-17" xy="1911, 2252, 2033, 2319">κν</word><word id="I-B27K3V18-27-PROV-18" xy="2032, 2254, 2203, 2321">[...]</word></line><line id="I-64-2v-1-23" xy="1394, 2314, 2836, 2378"><word id="I-B27K3V19-27-PROV-1" xy="1369, 2314, 1447, 2378">ο</word><word id="I-B27K3V19-27-PROV-2" xy="1453, 2310, 1561, 2377">θϲ</word><word id="I-B27K3V19-27-PROV-3" xy="1567, 2315, 1670, 2382">τη</word><word id="I-B27K3V19-27-PROV-4" xy="1681, 2317, 1927, 2384">ϲοφια</word><word id="I-B27K3V19-27-PROV-5" xy="1924, 2316, 2528, 2383">εθεμελιωϲεν</word><word id="I-B27K3V19-27-PROV-6" xy="2521, 2314, 2685, 2381">την</word><word id="I-B27K3V19-27-PROV-7" xy="2682, 2315, 2834, 2382">γην</word></line><line id="I-64-2v-1-24" xy="1396, 2382, 2861, 2446"><word id="I-B27K3V19-27-PROV-8" xy="1386, 2376, 1883, 2443">ητοιμαϲεν</word><word id="I-B27K3V19-27-PROV-9" xy="1895, 2379, 2001, 2446">δε</word><word id="I-B27K3V19-27-PROV-10" xy="1993, 2381, 2423, 2448">ουρανουϲ</word><word id="I-B27K3V19-27-PROV-11" xy="2424, 2367, 2446, 2434">[...]</word><word id="I-B27K3V19-27-PROV-12" xy="2434, 2382, 2829, 2449">φρονηϲει</word><word id="I-B27K3V19-27-PROV-13" xy="2841, 2378, 2866, 2445">·</word></line><line id="I-64-2v-1-25" xy="1399, 2442, 2669, 2506"><word id="I-B27K3V20-27-PROV-1" xy="1387, 2439, 1516, 2506">εν</word><word id="I-B27K3V20-27-PROV-2" xy="1519, 2440, 1898, 2507">αιϲθηϲει</word><word id="I-B27K3V20-27-PROV-3" xy="1891, 2441, 1909, 2508">[...]</word><word id="I-B27K3V20-27-PROV-4" xy="1897, 2441, 1925, 2508">·</word><word id="I-B27K3V20-27-PROV-5" xy="1916, 2442, 2226, 2509">αβυϲϲοι</word><word id="I-B27K3V20-27-PROV-6" xy="2232, 2442, 2674, 2509">ερραγηϲαν</word></line><line id="I-64-2v-1-26" xy="1397, 2500, 2555, 2564"><word id="I-B27K3V20-27-PROV-7" xy="1372, 2500, 1653, 2564">νεφη</word><word id="I-B27K3V20-27-PROV-8" xy="1653, 2500, 1765, 2564">δε</word><word id="I-B27K3V20-27-PROV-9" xy="1765, 2500, 2191, 2564">ερρυηϲαν</word><word id="I-B27K3V20-27-PROV-10" xy="2191, 2500, 2577, 2564">δροϲουϲ</word></line><line id="I-64-2v-1-27" xy="1382, 2563, 2105, 2627"><word id="I-B27K3V21-27-PROV-1" xy="1365, 2563, 1516, 2630">ϋϊε</word><word id="I-B27K3V21-27-PROV-2" xy="1511, 2565, 1540, 2632">·</word><word id="I-B27K3V21-27-PROV-3" xy="1531, 2561, 1669, 2628">μη</word><word id="I-B27K3V21-27-PROV-4" xy="1675, 2563, 2116, 2630">παραρυηϲ</word></line><line id="I-64-2v-1-28" xy="1375, 2624, 2664, 2688"><word id="I-B27K3V21-27-PROV-5" xy="1367, 2624, 1798, 2691">τηρηϲον</word><word id="I-B27K3V21-27-PROV-6" xy="1796, 2624, 1917, 2691">δε</word><word id="I-B27K3V21-27-PROV-7" xy="1912, 2623, 2186, 2690">εμην</word><word id="I-B27K3V21-27-PROV-8" xy="2167, 2624, 2516, 2688">βουλην</word><word id="I-B27K3V21-27-PROV-9" xy="2516, 2624, 2687, 2688">και</word></line><line id="I-64-2v-1-29" xy="1622, 2687, 2023, 2751"><word id="I-B27K3V21-27-PROV-10" xy="1597, 2687, 2048, 2751">εννοιαν</word></line><line id="I-64-2v-1-30" xy="1397, 2745, 2670, 2809"><word id="I-B27K3V22-27-PROV-1" xy="1376, 2745, 1544, 2812">ϊνα</word><word id="I-B27K3V22-27-PROV-2" xy="1537, 2745, 1777, 2809">ζηϲη</word><word id="I-B27K3V22-27-PROV-3" xy="1777, 2745, 1845, 2809">η</word><word id="I-B27K3V22-27-PROV-4" xy="1845, 2745, 2082, 2809">ψυχη</word><word id="I-B27K3V22-27-PROV-5" xy="2082, 2745, 2236, 2809">ϲου</word><word id="I-B27K3V22-27-PROV-6" xy="2236, 2745, 2373, 2809">και</word><word id="I-B27K3V22-27-PROV-7" xy="2373, 2745, 2598, 2809">χαριϲ</word><word id="I-B27K3V22-27-PROV-8" xy="2598, 2745, 2691, 2809">η</word></line><line id="I-64-2v-1-31" xy="1621, 2810, 2374, 2874"><word id="I-B27K3V22-27-PROV-9" xy="1615, 2810, 1827, 2877">περι</word><word id="I-B27K3V22-27-PROV-10" xy="1827, 2812, 1963, 2879">ϲω</word><word id="I-B27K3V22-27-PROV-11" xy="1961, 2812, 2348, 2879">τραχηλω</word><word id="I-B27K3V22-27-PROV-12" xy="2352, 2808, 2384, 2875">·</word></line><line id="I-64-2v-1-32" xy="1397, 2875, 2525, 2939"><word id="I-B27K3V22-27-PROV-13" xy="1392, 2875, 1636, 2942">εϲται</word><word id="I-B27K3V22-27-PROV-14" xy="1631, 2875, 1747, 2942">δε</word><word id="I-B27K3V22-27-PROV-15" xy="1740, 2876, 1967, 2943">ιαϲιϲ</word><word id="I-B27K3V22-27-PROV-16" xy="1967, 2875, 2148, 2942">ταιϲ</word><word id="I-B27K3V22-27-PROV-17" xy="2149, 2876, 2373, 2943">ϲαρξι</word><word id="I-B27K3V22-27-PROV-18" xy="2368, 2873, 2507, 2940">ϲου</word><word id="I-B27K3V22-27-PROV-19" xy="2506, 2875, 2530, 2942">·</word></line><line id="I-64-2v-1-33" xy="1403, 2940, 2616, 3004"><word id="I-B27K3V22-27-PROV-20" xy="1378, 2940, 1549, 3004">και</word><word id="I-B27K3V22-27-PROV-21" xy="1549, 2940, 1971, 3004">επιμελια</word><word id="I-B27K3V22-27-PROV-22" xy="1971, 2940, 2143, 3004">τοιϲ</word><word id="I-B27K3V22-27-PROV-23" xy="2143, 2940, 2278, 3004">οιϲ</word><word id="I-B27K3V22-27-PROV-24" xy="2272, 2943, 2616, 3010">οϲτεοιϲ</word></line><line id="I-64-2v-1-34" xy="1396, 3000, 2729, 3064"><word id="I-B27K3V23-27-PROV-1" xy="1391, 3004, 1554, 3071">ϊνα</word><word id="I-B27K3V23-27-PROV-2" xy="1553, 3003, 1883, 3070">πορευη</word><word id="I-B27K3V23-27-PROV-3" xy="1878, 3001, 2330, 3068">πεποιθωϲ</word><word id="I-B27K3V23-27-PROV-4" xy="2333, 3002, 2447, 3069">εν</word><word id="I-B27K3V23-27-PROV-5" xy="2447, 3001, 2708, 3068">ϊρηνη</word><word id="I-B27K3V23-27-PROV-6" xy="2708, 3003, 2740, 3070">·</word></line><line id="I-64-2v-1-35" xy="1612, 3060, 2426, 3124"><word id="I-B27K3V23-27-PROV-7" xy="1599, 3060, 1891, 3127">παϲαϲ</word><word id="I-B27K3V23-27-PROV-8" xy="1889, 3059, 2024, 3126">ταϲ</word><word id="I-B27K3V23-27-PROV-9" xy="2027, 3060, 2275, 3127">οδουϲ</word><word id="I-B27K3V23-27-PROV-10" xy="2272, 3060, 2449, 3124">ϲου</word></line><line id="I-64-2v-1-36" xy="1402, 3127, 2578, 3191"><word id="I-B27K3V23-27-PROV-11" xy="1391, 3123, 1466, 3190">ο</word><word id="I-B27K3V23-27-PROV-12" xy="1465, 3125, 1565, 3192">δε</word><word id="I-B27K3V23-27-PROV-13" xy="1567, 3127, 1764, 3194">πουϲ</word><word id="I-B27K3V23-27-PROV-14" xy="1763, 3125, 1900, 3192">ϲου</word><word id="I-B27K3V23-27-PROV-15" xy="1889, 3128, 1919, 3195">·</word><word id="I-B27K3V23-27-PROV-16" xy="1914, 3126, 2010, 3193">ου</word><word id="I-B27K3V23-27-PROV-17" xy="2012, 3127, 2133, 3191">μη</word><word id="I-B27K3V23-27-PROV-18" xy="2145, 3128, 2559, 3195">προϲκοψη</word><word id="I-B27K3V23-27-PROV-19" xy="2560, 3125, 2586, 3192">·</word></line><line id="I-64-2v-1-37" xy="1407, 3188, 2432, 3252"><word id="I-B27K3V24-27-PROV-1" xy="1396, 3188, 1574, 3255">εαν</word><word id="I-B27K3V24-27-PROV-2" xy="1570, 3190, 1701, 3257">γαρ</word><word id="I-B27K3V24-27-PROV-3" xy="1701, 3188, 1919, 3255">καθη</word><word id="I-B27K3V24-27-PROV-4" xy="1919, 3188, 1939, 3255">·</word><word id="I-B27K3V24-27-PROV-5" xy="1936, 3189, 2267, 3256">αφοβοϲ</word><word id="I-B27K3V24-27-PROV-6" xy="2266, 3193, 2413, 3260">εϲη</word><word id="I-B27K3V24-27-PROV-7" xy="2414, 3188, 2444, 3255">·</word></line><line id="I-64-2v-1-38" xy="1403, 3251, 2835, 3315"><word id="I-B27K3V24-27-PROV-8" xy="1400, 3253, 1583, 3320">εαν</word><word id="I-B27K3V24-27-PROV-9" xy="1590, 3250, 1696, 3317">δε</word><word id="I-B27K3V24-27-PROV-10" xy="1691, 3256, 2131, 3323">καθευδηϲ</word><word id="I-B27K3V24-27-PROV-11" xy="2128, 3255, 2148, 3322">·</word><word id="I-B27K3V24-27-PROV-12" xy="2141, 3255, 2437, 3322">ηδεωϲ</word><word id="I-B27K3V24-27-PROV-13" xy="2438, 3252, 2819, 3319">ϋπνωϲειϲ</word><word id="I-B27K3V24-27-PROV-14" xy="2820, 3257, 2843, 3324">.</word></line><line id="I-64-2v-1-39" xy="1405, 3322, 2563, 3386"><word id="I-B27K3V25-27-PROV-1" xy="1380, 3322, 1551, 3386">και</word><word id="I-B27K3V25-27-PROV-2" xy="1551, 3322, 1665, 3386">ου</word><word id="I-B27K3V25-27-PROV-3" xy="1665, 3322, 2176, 3386">φοβηθηϲη</word><word id="I-B27K3V25-27-PROV-4" xy="2176, 3322, 2586, 3386">πτοηϲιν</word></line><line id="I-64-2v-1-40" xy="1625, 3385, 2210, 3449"><word id="I-B27K3V25-27-PROV-5" xy="1628, 3380, 2190, 3447">επελθουϲαν</word><word id="I-B27K3V25-27-PROV-6" xy="2190, 3385, 2221, 3452">·</word></line><line id="I-64-2v-1-41" xy="1401, 3435, 2818, 3499"><word id="I-B27K3V25-27-PROV-7" xy="1385, 3435, 1619, 3502">ουδε</word><word id="I-B27K3V25-27-PROV-8" xy="1622, 3436, 1878, 3503">ορμαϲ</word><word id="I-B27K3V25-27-PROV-9" xy="1879, 3435, 2232, 3502">αϲεβων</word><word id="I-B27K3V25-27-PROV-10" xy="2222, 3435, 2806, 3502">επερχομεναϲ</word><word id="I-B27K3V25-27-PROV-11" xy="2802, 3433, 2826, 3500">·</word></line><line id="I-64-2v-1-42" xy="1399, 3491, 2833, 3555"><word id="I-B27K3V26-27-PROV-1" xy="1374, 3491, 1450, 3555">ο</word><word id="I-B27K3V26-27-PROV-2" xy="1455, 3495, 1594, 3562">γαρ</word><word id="I-B27K3V26-27-PROV-3" xy="1596, 3492, 1700, 3559">κϲ</word><word id="I-B27K3V26-27-PROV-4" xy="1706, 3494, 1931, 3561">εϲται</word><word id="I-B27K3V26-27-PROV-5" xy="1930, 3495, 1950, 3562">·</word><word id="I-B27K3V26-27-PROV-6" xy="1946, 3493, 2087, 3560">επι</word><word id="I-B27K3V26-27-PROV-7" xy="2097, 3499, 2431, 3566">παϲων</word><word id="I-B27K3V26-27-PROV-8" xy="2431, 3499, 2686, 3566">οδων</word><word id="I-B27K3V26-27-PROV-9" xy="2703, 3493, 2817, 3560">ϲου</word><word id="I-B27K3V26-27-PROV-10" xy="2813, 3489, 2844, 3556">·</word></line><line id="I-64-2v-1-43" xy="1408, 3554, 2853, 3618"><word id="I-B27K3V26-27-PROV-11" xy="1383, 3554, 1528, 3618">και</word><word id="I-B27K3V26-27-PROV-12" xy="1541, 3561, 1829, 3628">ερειϲει</word><word id="I-B27K3V26-27-PROV-13" xy="1842, 3555, 2009, 3622">ϲον</word><word id="I-B27K3V26-27-PROV-14" xy="2013, 3558, 2229, 3625">ποδα</word><word id="I-B27K3V26-27-PROV-15" xy="2220, 3557, 2248, 3624">·</word><word id="I-B27K3V26-27-PROV-16" xy="2242, 3560, 2389, 3627">ϊνα</word><word id="I-B27K3V26-27-PROV-17" xy="2391, 3558, 2516, 3625">μη</word><word id="I-B27K3V26-27-PROV-18" xy="2522, 3558, 2838, 3625">ϲαλευθηϲ</word><word id="I-B27K3V26-27-PROV-19" xy="2836, 3558, 2861, 3625">·</word></line><line id="I-64-2v-1-44" xy="1401, 3623, 2574, 3687"><word id="I-B27K3V27-27-PROV-1" xy="1376, 3623, 1534, 3687">μη</word><word id="I-B27K3V27-27-PROV-2" xy="1541, 3622, 1893, 3689">αποϲχη</word><word id="I-B27K3V27-27-PROV-3" xy="1894, 3621, 1997, 3688">ευ</word><word id="I-B27K3V27-27-PROV-4" xy="2001, 3619, 2279, 3686">ποιειν</word><word id="I-B27K3V27-27-PROV-5" xy="2283, 3620, 2559, 3687">ενδεη</word><word id="I-B27K3V27-27-PROV-6" xy="2554, 3625, 2581, 3692">·</word></line><line id="I-64-2v-1-45" xy="1398, 3687, 2721, 3751"><word id="I-B27K3V27-27-PROV-7" xy="1391, 3687, 1686, 3754">ηνικα</word><word id="I-B27K3V27-27-PROV-8" xy="1690, 3686, 1807, 3753">αν</word><word id="I-B27K3V27-27-PROV-9" xy="1807, 3686, 1987, 3753">εχη</word><word id="I-B27K3V27-27-PROV-10" xy="1987, 3687, 2057, 3754">η</word><word id="I-B27K3V27-27-PROV-11" xy="2048, 3689, 2176, 3756">χιρ</word><word id="I-B27K3V27-27-PROV-12" xy="2176, 3683, 2332, 3750">ϲου</word><word id="I-B27K3V27-27-PROV-13" xy="2331, 3687, 2697, 3754">βοηθειν</word><word id="I-B27K3V27-27-PROV-14" xy="2702, 3687, 2732, 3754">·</word></line><line id="I-64-2v-1-46" xy="1396, 3738, 2758, 3802"><word id="I-B27K3V28-27-PROV-1" xy="1371, 3738, 1547, 3802">μη</word><word id="I-B27K3V28-27-PROV-2" xy="1547, 3738, 1830, 3802">ειπηϲ</word><word id="I-B27K3V28-27-PROV-3" xy="1829, 3737, 2348, 3804">επανελθων</word><word id="I-B27K3V28-27-PROV-4" xy="2356, 3737, 2648, 3804">επανη</word></line><line id="I-64-2v-1-47" xy="1628, 3799, 2330, 3863"><word id="I-B27K3V28-27-PROV-6" xy="1619, 3799, 1782, 3866">και</word><word id="I-B27K3V28-27-PROV-7" xy="1775, 3799, 2064, 3866">αυριον</word><word id="I-B27K3V28-27-PROV-8" xy="2064, 3798, 2343, 3865">δωϲω</word></line><line id="I-64-2v-1-48" xy="1396, 3863, 2570, 3927"><word id="I-B27K3V28-27-PROV-9" xy="1376, 3862, 1747, 3929">δυνατου</word><word id="I-B27K3V28-27-PROV-10" xy="1747, 3865, 1900, 3932">ϲου</word><word id="I-B27K3V28-27-PROV-11" xy="1905, 3864, 2175, 3931">οντοϲ</word><word id="I-B27K3V28-27-PROV-12" xy="2176, 3863, 2281, 3930">ευ</word><word id="I-B27K3V28-27-PROV-13" xy="2272, 3863, 2555, 3930">ποιειν</word><word id="I-B27K3V28-27-PROV-14" xy="2547, 3863, 2576, 3930">·</word></line></col><col id="I-64-2v-2" xy="3102, 985, 4556, 3935"><line id="I-64-2v-2-1" xy="3134, 977, 4353, 1041"><word id="I-B27K3V28-27-PROV-15" xy="3109, 977, 3228, 1041">ου</word><word id="I-B27K3V28-27-PROV-16" xy="3228, 977, 3355, 1041">γαρ</word><word id="I-B27K3V28-27-PROV-17" xy="3362, 972, 3588, 1039">οιδαϲ</word><word id="I-B27K3V28-27-PROV-18" xy="3584, 976, 3615, 1043">·</word><word id="I-B27K3V28-27-PROV-19" xy="3612, 973, 3668, 1040">τι</word><word id="I-B27K3V28-27-PROV-20" xy="3676, 975, 3963, 1042">τεξεται</word><word id="I-B27K3V28-27-PROV-21" xy="3962, 977, 4025, 1044">η</word><word id="I-B27K3V28-27-PROV-22" xy="4027, 977, 4342, 1044">επιουϲα</word><word id="I-B27K3V28-27-PROV-23" xy="4335, 976, 4365, 1043">·</word></line><line id="I-64-2v-2-2" xy="3137, 1037, 4492, 1101"><word id="I-B27K3V29-27-PROV-1" xy="3112, 1037, 3274, 1101">μη</word><word id="I-B27K3V29-27-PROV-2" xy="3280, 1036, 3659, 1103">τεκτηνη</word><word id="I-B27K3V29-27-PROV-3" xy="3673, 1038, 3820, 1105">επι</word><word id="I-B27K3V29-27-PROV-4" xy="3822, 1040, 3987, 1107">ϲον</word><word id="I-B27K3V29-27-PROV-5" xy="4003, 1045, 4265, 1112">φιλον</word><word id="I-B27K3V29-27-PROV-6" xy="4271, 1040, 4484, 1107">κακα</word><word id="I-B27K3V29-27-PROV-7" xy="4480, 1035, 4494, 1102">·</word></line><line id="I-64-2v-2-3" xy="3134, 1099, 4552, 1163"><word id="I-B27K3V29-27-PROV-8" xy="3139, 1100, 3718, 1167">παροικουντα</word><word id="I-B27K3V29-27-PROV-9" xy="3725, 1100, 3863, 1167">και</word><word id="I-B27K3V29-27-PROV-10" xy="3865, 1103, 4331, 1170">πεποιθοτα</word><word id="I-B27K3V29-27-PROV-11" xy="4331, 1103, 4477, 1170">επι</word><word id="I-B27K3V29-27-PROV-12" xy="4467, 1101, 4564, 1168">ϲοι</word></line><line id="I-64-2v-2-4" xy="3128, 1168, 4672, 1232"><word id="I-B27K3V30-27-PROV-1" xy="3125, 1162, 3283, 1229">μη</word><word id="I-B27K3V30-27-PROV-2" xy="3272, 1168, 3880, 1235">φιλεχθρηϲηϲ</word><word id="I-B27K3V30-27-PROV-3" xy="3883, 1170, 4093, 1237">προϲ</word><word id="I-B27K3V30-27-PROV-4" xy="4095, 1173, 4561, 1240">ανθρωπον</word><word id="I-B27K3V30-27-PROV-5" xy="4553, 1172, 4681, 1239">ματη</word></line><line id="I-64-2v-2-5" xy="3130, 1228, 4083, 1292"><word id="I-B27K3V30-27-PROV-6" xy="3114, 1228, 3266, 1295">μη</word><word id="I-B27K3V30-27-PROV-7" xy="3265, 1228, 3350, 1295">τι</word><word id="I-B27K3V30-27-PROV-8" xy="3335, 1230, 3365, 1297">[...]</word><word id="I-B27K3V30-27-PROV-10" xy="3354, 1233, 3773, 1300">εργαϲηται</word><word id="I-B27K3V30-27-PROV-11" xy="3774, 1227, 4053, 1294">κακον</word><word id="I-B27K3V30-27-PROV-12" xy="4059, 1228, 4092, 1295">·</word></line><line id="I-64-2v-2-6" xy="3129, 1293, 4479, 1357"><word id="I-B27K3V31-27-PROV-1" xy="3104, 1293, 3260, 1357">μη</word><word id="I-B27K3V31-27-PROV-2" xy="3273, 1294, 3537, 1361">κτηϲη</word><word id="I-B27K3V31-27-PROV-3" xy="3551, 1294, 3859, 1361">κακων</word><word id="I-B27K3V31-27-PROV-4" xy="3867, 1293, 4217, 1360">ανδρων</word><word id="I-B27K3V31-27-PROV-5" xy="4225, 1297, 4465, 1364">ονιδη</word><word id="I-B27K3V31-27-PROV-6" xy="4462, 1293, 4491, 1360">·</word></line><line id="I-64-2v-2-7" xy="3131, 1352, 4509, 1416"><word id="I-B27K3V31-27-PROV-7" xy="3117, 1352, 3387, 1419">μηδε</word><word id="I-B27K3V31-27-PROV-8" xy="3385, 1352, 3800, 1419">ζηλωϲηϲ</word><word id="I-B27K3V31-27-PROV-9" xy="3818, 1354, 3951, 1421">ταϲ</word><word id="I-B27K3V31-27-PROV-10" xy="3950, 1354, 4212, 1421">οδουϲ</word><word id="I-B27K3V31-27-PROV-11" xy="4201, 1354, 4486, 1421">αυτων</word><word id="I-B27K3V31-27-PROV-12" xy="4488, 1355, 4522, 1422">·</word></line><line id="I-64-2v-2-8" xy="3133, 1413, 4603, 1477"><word id="I-B27K3V32-27-PROV-1" xy="3118, 1414, 3619, 1481">ακαθαρτοϲ</word><word id="I-B27K3V32-27-PROV-2" xy="3624, 1421, 3984, 1488">εναντι</word><word id="I-B27K3V32-27-PROV-3" xy="3981, 1419, 4087, 1486">κυ</word><word id="I-B27K3V32-27-PROV-4" xy="4083, 1420, 4111, 1487">·</word><word id="I-B27K3V32-27-PROV-5" xy="4100, 1416, 4258, 1483">παϲ</word><word id="I-B27K3V32-27-PROV-6" xy="4257, 1417, 4603, 1484">παρανομοϲ</word></line><line id="I-64-2v-2-9" xy="3124, 1472, 4390, 1536"><word id="I-B27K3V32-27-PROV-7" xy="3106, 1471, 3245, 1538">εν</word><word id="I-B27K3V32-27-PROV-8" xy="3244, 1472, 3354, 1539">δε</word><word id="I-B27K3V32-27-PROV-9" xy="3357, 1470, 3723, 1537">δικαιοιϲ</word><word id="I-B27K3V32-27-PROV-10" xy="3719, 1472, 3735, 1539">·</word><word id="I-B27K3V32-27-PROV-11" xy="3737, 1472, 3842, 1539">ου</word><word id="I-B27K3V32-27-PROV-12" xy="3838, 1473, 4369, 1540">ϲυνεδριαζει</word><word id="I-B27K3V32-27-PROV-13" xy="4374, 1480, 4396, 1547">·</word></line><line id="I-64-2v-2-10" xy="3127, 1536, 4306, 1600"><word id="I-B27K3V33-27-PROV-1" xy="3114, 1536, 3410, 1603">καταρα</word><word id="I-B27K3V33-27-PROV-2" xy="3407, 1536, 3507, 1603">θυ</word><word id="I-B27K3V33-27-PROV-3" xy="3499, 1535, 3523, 1602">·</word><word id="I-B27K3V33-27-PROV-4" xy="3516, 1535, 3630, 1602">εν</word><word id="I-B27K3V33-27-PROV-5" xy="3639, 1537, 3924, 1604">οικοιϲ</word><word id="I-B27K3V33-27-PROV-6" xy="3924, 1535, 4281, 1602">αϲεβων</word><word id="I-B27K3V33-27-PROV-7" xy="4288, 1536, 4309, 1603">·</word></line><line id="I-64-2v-2-11" xy="3123, 1598, 4556, 1662"><word id="I-B27K3V33-27-PROV-8" xy="3098, 1598, 3511, 1662">επαυλειϲ</word><word id="I-B27K3V33-27-PROV-9" xy="3511, 1598, 3618, 1662">δε</word><word id="I-B27K3V33-27-PROV-10" xy="3621, 1600, 4014, 1667">δικαιων</word><word id="I-B27K3V33-27-PROV-11" xy="4013, 1599, 4539, 1666">ευλογουνται</word><word id="I-B27K3V33-27-PROV-12" xy="4540, 1600, 4571, 1667">·</word></line><line id="I-64-2v-2-12" xy="3127, 1661, 4419, 1725"><word id="I-B27K3V34-27-PROV-1" xy="3102, 1661, 3235, 1725">κϲ</word><word id="I-B27K3V34-27-PROV-2" xy="3230, 1662, 3862, 1729">υπερηφανοιϲ</word><word id="I-B27K3V34-27-PROV-3" xy="3861, 1663, 4402, 1730">αντιταϲϲεται</word><word id="I-B27K3V34-27-PROV-4" xy="4404, 1662, 4434, 1729">·</word></line><line id="I-64-2v-2-13" xy="3101, 1723, 4271, 1787"><word id="I-B27K3V34-27-PROV-5" xy="3110, 1723, 3517, 1790">ταπινοιϲ</word><word id="I-B27K3V34-27-PROV-6" xy="3520, 1723, 3625, 1790">δε</word><word id="I-B27K3V34-27-PROV-7" xy="3618, 1722, 3997, 1789">διδωϲιν</word><word id="I-B27K3V34-27-PROV-8" xy="3997, 1723, 4247, 1790">χαριν</word><word id="I-B27K3V34-27-PROV-9" xy="4252, 1722, 4285, 1789">·</word></line><line id="I-64-2v-2-14" xy="3121, 1782, 4506, 1846"><word id="I-B27K3V35-27-PROV-1" xy="3096, 1782, 3385, 1846">δοξαν</word><word id="I-B27K3V35-27-PROV-2" xy="3379, 1778, 3404, 1845">·</word><word id="I-B27K3V35-27-PROV-3" xy="3404, 1782, 3660, 1849">ϲοφοι</word><word id="I-B27K3V35-27-PROV-4" xy="3668, 1786, 4490, 1853">κληρονομηϲουϲιν</word><word id="I-B27K3V35-27-PROV-5" xy="4487, 1788, 4520, 1855">·</word></line><line id="I-64-2v-2-15" xy="3119, 1841, 4342, 1905"><word id="I-B27K3V35-27-PROV-6" xy="3094, 1841, 3198, 1905">οι</word><word id="I-B27K3V35-27-PROV-7" xy="3198, 1841, 3308, 1905">δε</word><word id="I-B27K3V35-27-PROV-8" xy="3308, 1841, 3623, 1905">αϲεβειϲ</word><word id="I-B27K3V35-27-PROV-9" xy="3620, 1841, 3651, 1908">·</word><word id="I-B27K3V35-27-PROV-10" xy="3648, 1843, 4011, 1910">υψωϲαν</word><word id="I-B27K3V35-27-PROV-11" xy="4012, 1842, 4346, 1909">ατιμιαν</word></line><line id="I-64-2v-2-16" xy="3106, 1905, 4528, 1969"><word id="I-B27K4V1-27-PROV-1" xy="3100, 1905, 3502, 1972">ακουϲατε</word><word id="I-B27K4V1-27-PROV-2" xy="3504, 1904, 3799, 1971">παιδεϲ</word><word id="I-B27K4V1-27-PROV-3" xy="3788, 1905, 3816, 1972">·</word><word id="I-B27K4V1-27-PROV-4" xy="3810, 1906, 4213, 1973">παιδειαν</word><word id="I-B27K4V1-27-PROV-5" xy="4213, 1907, 4511, 1974">πατροϲ</word><word id="I-B27K4V1-27-PROV-6" xy="4513, 1910, 4539, 1977">·</word></line><line id="I-64-2v-2-17" xy="3119, 1967, 4485, 2031"><word id="I-B27K4V1-27-PROV-7" xy="3109, 1969, 3274, 2036">και</word><word id="I-B27K4V1-27-PROV-8" xy="3275, 1968, 3740, 2035">προϲεχετε</word><word id="I-B27K4V1-27-PROV-9" xy="3732, 1967, 4075, 2034">γνωναι</word><word id="I-B27K4V1-27-PROV-10" xy="4073, 1968, 4471, 2035">εννοιαν</word><word id="I-B27K4V1-27-PROV-11" xy="4471, 1969, 4496, 2036">·</word></line><line id="I-64-2v-2-18" xy="3107, 2031, 4544, 2095"><word id="I-B27K4V2-27-PROV-1" xy="3108, 2031, 3437, 2098">δωρον</word><word id="I-B27K4V2-27-PROV-2" xy="3433, 2030, 3569, 2097">γαρ</word><word id="I-B27K4V2-27-PROV-3" xy="3570, 2028, 3880, 2095">αγαθον</word><word id="I-B27K4V2-27-PROV-4" xy="3883, 2031, 3907, 2098">·</word><word id="I-B27K4V2-27-PROV-5" xy="3895, 2030, 4324, 2097">δωρουμαι</word><word id="I-B27K4V2-27-PROV-6" xy="4324, 2034, 4523, 2101">υμιν</word><word id="I-B27K4V2-27-PROV-7" xy="4528, 2030, 4553, 2097">·</word></line><line id="I-64-2v-2-19" xy="3099, 2089, 4592, 2153"><word id="I-B27K4V2-27-PROV-8" xy="3102, 2086, 3281, 2153">τον</word><word id="I-B27K4V2-27-PROV-9" xy="3290, 2086, 3533, 2153">εμον</word><word id="I-B27K4V2-27-PROV-10" xy="3556, 2088, 3864, 2155">νομον</word><word id="I-B27K4V2-27-PROV-11" xy="3870, 2089, 3889, 2156">·</word><word id="I-B27K4V2-27-PROV-12" xy="3880, 2087, 4022, 2154">μη</word><word id="I-B27K4V2-27-PROV-13" xy="4018, 2087, 4570, 2154">εγκαταλιπητε</word><word id="I-B27K4V2-27-PROV-14" xy="4574, 2090, 4603, 2157">:</word></line><line id="I-64-2v-2-20" xy="3100, 2155, 4696, 2219"><word id="I-B27K4V3-27-PROV-1" xy="3092, 2152, 3285, 2219">ϋϊοϲ</word><word id="I-B27K4V3-27-PROV-2" xy="3290, 2149, 3427, 2216">γαρ</word><word id="I-B27K4V3-27-PROV-3" xy="3423, 2153, 3904, 2220">εγενομην</word><word id="I-B27K4V3-27-PROV-4" xy="3913, 2153, 4149, 2220">καγω</word><word id="I-B27K4V3-27-PROV-5" xy="4149, 2150, 4168, 2217">.</word><word id="I-B27K4V3-27-PROV-6" xy="4165, 2150, 4382, 2217">πατρι</word><word id="I-B27K4V3-27-PROV-7" xy="4380, 2154, 4684, 2221">ϋπηκοοϲ</word><word id="I-B27K4V3-27-PROV-8" xy="4681, 2154, 4705, 2221">·</word></line><line id="I-64-2v-2-21" xy="3117, 2212, 4628, 2276"><word id="I-B27K4V3-27-PROV-9" xy="3104, 2211, 3255, 2278">και</word><word id="I-B27K4V3-27-PROV-10" xy="3257, 2204, 3830, 2271">αγαπωμενοϲ</word><word id="I-B27K4V3-27-PROV-11" xy="3821, 2202, 3846, 2269">·</word><word id="I-B27K4V3-27-PROV-12" xy="3846, 2201, 3952, 2268">εν</word><word id="I-B27K4V3-27-PROV-13" xy="3957, 2206, 4386, 2273">προϲωπω</word><word id="I-B27K4V3-27-PROV-14" xy="4389, 2210, 4619, 2277">μητροϲ</word></line><line id="I-64-2v-2-22" xy="3112, 2260, 4275, 2324"><word id="I-B27K4V4-27-PROV-1" xy="3100, 2261, 3201, 2328">ὁι</word><word id="I-B27K4V4-27-PROV-2" xy="3202, 2258, 3522, 2325">ελεγον</word><word id="I-B27K4V4-27-PROV-3" xy="3523, 2259, 3543, 2326">·</word><word id="I-B27K4V4-27-PROV-4" xy="3535, 2260, 3664, 2324">και</word><word id="I-B27K4V4-27-PROV-5" xy="3684, 2262, 4131, 2329">εδιδαϲκον</word><word id="I-B27K4V4-27-PROV-6" xy="4144, 2260, 4263, 2327">με</word><word id="I-B27K4V4-27-PROV-7" xy="4260, 2262, 4288, 2329">·</word></line><line id="I-64-2v-2-23" xy="3116, 2319, 4316, 2383"><word id="I-B27K4V4-27-PROV-8" xy="3106, 2321, 3528, 2388">ερειδετω</word><word id="I-B27K4V4-27-PROV-9" xy="3532, 2321, 3592, 2388">ο</word><word id="I-B27K4V4-27-PROV-10" xy="3602, 2319, 4047, 2383">ημετεροϲ</word><word id="I-B27K4V4-27-PROV-11" xy="4052, 2322, 4303, 2389">λογοϲ</word><word id="I-B27K4V4-27-PROV-12" xy="4306, 2322, 4327, 2389">.</word></line><line id="I-64-2v-2-24" xy="3334, 2388, 4113, 2452"><word id="I-B27K4V4-27-PROV-13" xy="3323, 2388, 3480, 2455">ειϲ</word><word id="I-B27K4V4-27-PROV-14" xy="3475, 2386, 3663, 2453">ϲην</word><word id="I-B27K4V4-27-PROV-15" xy="3664, 2388, 4088, 2455">διανοιαν</word><word id="I-B27K4V4-27-PROV-16" xy="4094, 2388, 4116, 2455">·</word></line><line id="I-64-2v-2-25" xy="3087, 2455, 4433, 2519"><word id="I-B27K4V5-27-PROV-1" xy="3104, 2452, 3464, 2519">φυλαϲϲε</word><word id="I-B27K4V5-27-PROV-2" xy="3465, 2455, 3829, 2522">εντολαϲ</word><word id="I-B27K4V5-27-PROV-3" xy="3830, 2419, 3859, 2486">[...]</word><word id="I-B27K4V5-27-PROV-4" xy="3834, 2456, 3851, 2523">·</word><word id="I-B27K4V5-27-PROV-5" xy="3854, 2454, 3981, 2521">μη</word><word id="I-B27K4V5-27-PROV-6" xy="4001, 2455, 4361, 2522">επιλαθη</word><word id="I-B27K4V5-27-PROV-7" xy="4364, 2455, 4381, 2522">.</word><word id="I-B27K4V5-27-PROV-8" xy="4385, 2455, 4506, 2522">[...]</word></line><line id="I-64-2v-2-26" xy="3112, 2519, 4592, 2583"><word id="I-B27K4V5-27-PROV-13" xy="3100, 2519, 3371, 2586">μηδε</word><word id="I-B27K4V5-27-PROV-14" xy="3368, 2515, 3731, 2582">παριδηϲ</word><word id="I-B27K4V5-27-PROV-15" xy="3731, 2519, 3973, 2586">ρηϲιν</word><word id="I-B27K4V5-27-PROV-16" xy="3974, 2515, 3999, 2582">·</word><word id="I-B27K4V5-27-PROV-17" xy="3996, 2519, 4220, 2583">εμου</word><word id="I-B27K4V5-27-PROV-18" xy="4220, 2519, 4614, 2583">ϲτοματοϲ</word></line><line id="I-64-2v-2-27" xy="3113, 2569, 4256, 2633"><word id="I-B27K4V6-27-PROV-1" xy="3091, 2569, 3369, 2636">μηδε</word><word id="I-B27K4V6-27-PROV-2" xy="3370, 2570, 3971, 2637">ενκαταλιπηϲ</word><word id="I-B27K4V6-27-PROV-3" xy="3973, 2574, 4246, 2641">αυτην</word><word id="I-B27K4V6-27-PROV-4" xy="4247, 2573, 4269, 2640">.</word></line><line id="I-64-2v-2-28" xy="3335, 2634, 4098, 2698"><word id="I-B27K4V6-27-PROV-5" xy="3310, 2634, 3468, 2698">και</word><word id="I-B27K4V6-27-PROV-6" xy="3472, 2634, 3922, 2701">ανθεξεται</word><word id="I-B27K4V6-27-PROV-7" xy="3929, 2634, 4081, 2701">ϲου</word><word id="I-B27K4V6-27-PROV-8" xy="4082, 2635, 4106, 2702">·</word></line><line id="I-64-2v-2-29" xy="3105, 2697, 4299, 2761"><word id="I-B27K4V6-27-PROV-9" xy="3106, 2697, 3481, 2764">εραϲθητι</word><word id="I-B27K4V6-27-PROV-10" xy="3486, 2697, 3734, 2764">αυτηϲ</word><word id="I-B27K4V6-27-PROV-11" xy="3728, 2697, 3744, 2764">·</word><word id="I-B27K4V6-27-PROV-12" xy="3753, 2697, 3880, 2764">και</word><word id="I-B27K4V6-27-PROV-13" xy="3881, 2697, 4190, 2764">τηρηϲει</word><word id="I-B27K4V6-27-PROV-14" xy="4190, 2697, 4283, 2764">ϲε</word><word id="I-B27K4V6-27-PROV-15" xy="4285, 2696, 4304, 2763">·</word></line><line id="I-64-2v-2-30" xy="3117, 2766, 4616, 2830"><word id="I-B27K4V8-27-PROV-1" xy="3109, 2763, 3826, 2830">περιχαρακωϲον</word><word id="I-B27K4V8-27-PROV-2" xy="3836, 2763, 4106, 2830">αυτην</word><word id="I-B27K4V8-27-PROV-3" xy="4103, 2767, 4127, 2834">·</word><word id="I-B27K4V8-27-PROV-4" xy="4115, 2763, 4243, 2830">και</word><word id="I-B27K4V8-27-PROV-5" xy="4246, 2764, 4543, 2831">ϋψωϲει</word><word id="I-B27K4V8-27-PROV-6" xy="4534, 2761, 4606, 2828">ϲε</word><word id="I-B27K4V8-27-PROV-7" xy="4602, 2762, 4629, 2829">·</word></line><line id="I-64-2v-2-31" xy="3092, 2824, 4407, 2888"><word id="I-B27K4V8-27-PROV-8" xy="3108, 2824, 3483, 2891">τιμηϲον</word><word id="I-B27K4V8-27-PROV-9" xy="3483, 2827, 3744, 2894">αυτην</word><word id="I-B27K4V8-27-PROV-10" xy="3741, 2827, 3765, 2894">·</word><word id="I-B27K4V8-27-PROV-11" xy="3759, 2825, 3896, 2892">ϊνα</word><word id="I-B27K4V8-27-PROV-12" xy="3901, 2826, 3999, 2893">ϲε</word><word id="I-B27K4V8-27-PROV-13" xy="3999, 2825, 4383, 2892">περιλαβη</word><word id="I-B27K4V8-27-PROV-14" xy="4388, 2825, 4411, 2892">·</word></line><line id="I-64-2v-2-32" xy="3109, 2886, 4475, 2950"><word id="I-B27K4V9-27-PROV-1" xy="3084, 2886, 3251, 2950">ϊνα</word><word id="I-B27K4V9-27-PROV-2" xy="3251, 2886, 3400, 2950">δω</word><word id="I-B27K4V9-27-PROV-3" xy="3400, 2886, 3504, 2950">τη</word><word id="I-B27K4V9-27-PROV-4" xy="3524, 2886, 3643, 2953">ϲη</word><word id="I-B27K4V9-27-PROV-5" xy="3640, 2886, 3999, 2953">κεφαλη</word><word id="I-B27K4V9-27-PROV-6" xy="3994, 2889, 4016, 2956">·</word><word id="I-B27K4V9-27-PROV-7" xy="4006, 2888, 4476, 2955">ϲτεφανον</word></line><line id="I-64-2v-2-33" xy="3316, 2951, 3718, 3015"><word id="I-B27K4V9-27-PROV-8" xy="3314, 2951, 3693, 3018">χαριτων</word><word id="I-B27K4V9-27-PROV-9" xy="3698, 2951, 3722, 3018">·</word></line><line id="I-64-2v-2-34" xy="3089, 3015, 4559, 3079"><word id="I-B27K4V9-27-PROV-10" xy="3088, 3015, 3506, 3082">τρεφανω</word><word id="I-B27K4V9-27-PROV-11" xy="3507, 3015, 3613, 3082">δε</word><word id="I-B27K4V9-27-PROV-12" xy="3612, 3012, 3923, 3079">τρυφηϲ</word><word id="I-B27K4V9-27-PROV-13" xy="3911, 3014, 3937, 3081">·</word><word id="I-B27K4V9-27-PROV-14" xy="3933, 3015, 4421, 3082">ϋπεραϲπιϲη</word><word id="I-B27K4V9-27-PROV-15" xy="4426, 3015, 4544, 3082">ϲου</word><word id="I-B27K4V9-27-PROV-16" xy="4541, 3016, 4568, 3083">:</word></line><line id="I-64-2v-2-35" xy="3100, 3075, 4497, 3139"><word id="I-B27K4V10-27-PROV-1" xy="3098, 3075, 3385, 3142">ακουε</word><word id="I-B27K4V10-27-PROV-2" xy="3388, 3077, 3513, 3144">ϋϊε</word><word id="I-B27K4V10-27-PROV-3" xy="3509, 3075, 3534, 3142">·</word><word id="I-B27K4V10-27-PROV-4" xy="3531, 3075, 3662, 3139">και</word><word id="I-B27K4V10-27-PROV-5" xy="3672, 3077, 3927, 3144">δεξαι</word><word id="I-B27K4V10-27-PROV-6" xy="3927, 3075, 4195, 3142">εμουϲ</word><word id="I-B27K4V10-27-PROV-7" xy="4187, 3074, 4482, 3141">λογουϲ</word><word id="I-B27K4V10-27-PROV-8" xy="4479, 3075, 4508, 3142">·</word></line><line id="I-64-2v-2-36" xy="3113, 3136, 4544, 3200"><word id="I-B27K4V10-27-PROV-9" xy="3097, 3138, 3250, 3205">και</word><word id="I-B27K4V10-27-PROV-10" xy="3253, 3139, 3982, 3206">πληθυνθηϲεται</word><word id="I-B27K4V10-27-PROV-11" xy="3980, 3117, 4046, 3166">[...]</word><word id="I-B27K4V10-27-PROV-12" xy="3982, 3137, 4136, 3204">ετη</word><word id="I-B27K4V10-27-PROV-13" xy="4147, 3136, 4388, 3203">ζωηϲ</word><word id="I-B27K4V10-27-PROV-14" xy="4387, 3136, 4530, 3203">ϲου</word><word id="I-B27K4V10-27-PROV-15" xy="4527, 3136, 4553, 3203">·</word></line><line id="I-64-2v-2-37" xy="3116, 3198, 4573, 3262"><word id="I-B27K4V10-27-PROV-16" xy="3091, 3198, 3258, 3262">ϊνα</word><word id="I-B27K4V10-27-PROV-17" xy="3270, 3198, 3401, 3265">ϲοι</word><word id="I-B27K4V10-27-PROV-18" xy="3414, 3199, 3851, 3266">γενωνται</word><word id="I-B27K4V10-27-PROV-19" xy="3849, 3200, 3876, 3267">·</word><word id="I-B27K4V10-27-PROV-20" xy="3866, 3198, 4179, 3265">πολλαι</word><word id="I-B27K4V10-27-PROV-21" xy="4176, 3198, 4372, 3262">οδοι</word><word id="I-B27K4V10-27-PROV-22" xy="4379, 3198, 4557, 3265">βιου</word><word id="I-B27K4V10-27-PROV-23" xy="4558, 3198, 4581, 3265">:</word></line><line id="I-64-2v-2-38" xy="3110, 3258, 4331, 3322"><word id="I-B27K4V11-27-PROV-1" xy="3103, 3258, 3381, 3325">οδουϲ</word><word id="I-B27K4V11-27-PROV-2" xy="3375, 3258, 3512, 3325">γαρ</word><word id="I-B27K4V11-27-PROV-3" xy="3514, 3259, 3822, 3326">ϲοφιαϲ</word><word id="I-B27K4V11-27-PROV-4" xy="3821, 3259, 3843, 3326">·</word><word id="I-B27K4V11-27-PROV-5" xy="3836, 3258, 4205, 3325">διδαϲκω</word><word id="I-B27K4V11-27-PROV-6" xy="4217, 3260, 4313, 3327">ϲε</word><word id="I-B27K4V11-27-PROV-7" xy="4310, 3257, 4340, 3324">·</word></line><line id="I-64-2v-2-39" xy="3108, 3316, 4537, 3380"><word id="I-B27K4V11-27-PROV-8" xy="3110, 3317, 3614, 3384">εμβιβαζω</word><word id="I-B27K4V11-27-PROV-9" xy="3619, 3323, 3715, 3390">δε</word><word id="I-B27K4V11-27-PROV-10" xy="3713, 3322, 3822, 3389">ϲε</word><word id="I-B27K4V11-27-PROV-11" xy="3810, 3324, 3837, 3391">·</word><word id="I-B27K4V11-27-PROV-12" xy="3833, 3323, 4221, 3390">τροχιᾶιϲ</word><word id="I-B27K4V11-27-PROV-13" xy="4219, 3320, 4512, 3387">ορθαιϲ</word><word id="I-B27K4V11-27-PROV-14" xy="4520, 3318, 4540, 3385">:</word></line><line id="I-64-2v-2-40" xy="3106, 3387, 4460, 3451"><word id="I-B27K4V12-27-PROV-1" xy="3086, 3387, 3283, 3454">εαν</word><word id="I-B27K4V12-27-PROV-2" xy="3278, 3389, 3421, 3456">γαρ</word><word id="I-B27K4V12-27-PROV-3" xy="3429, 3390, 3763, 3457">πορευη</word><word id="I-B27K4V12-27-PROV-4" xy="3756, 3390, 3788, 3457">·</word><word id="I-B27K4V12-27-PROV-5" xy="3780, 3387, 3887, 3454">ου</word><word id="I-B27K4V12-27-PROV-6-1" xy="3886, 3388, 4474, 3455">ϲυνκλιϲθηϲε</word></line><line id="I-64-2v-2-41" xy="3309, 3442, 4194, 3506"><word id="I-B27K4V12-27-PROV-6-2" xy="3318, 3444, 3463, 3511">ται</word><word id="I-B27K4V12-27-PROV-7" xy="3454, 3444, 3618, 3511">ϲου</word><word id="I-B27K4V12-27-PROV-8" xy="3620, 3445, 3714, 3512">τα</word><word id="I-B27K4V12-27-PROV-9" xy="3712, 3442, 4175, 3509">διαβηματα</word><word id="I-B27K4V12-27-PROV-10" xy="4172, 3443, 4208, 3510">·</word></line><line id="I-64-2v-2-42" xy="3104, 3504, 4333, 3568"><word id="I-B27K4V12-27-PROV-11" xy="3103, 3504, 3275, 3571">εαν</word><word id="I-B27K4V12-27-PROV-12" xy="3275, 3504, 3371, 3571">δε</word><word id="I-B27K4V12-27-PROV-13" xy="3365, 3502, 3699, 3569">τρεχηϲ</word><word id="I-B27K4V12-27-PROV-14" xy="3688, 3504, 3717, 3571">·</word><word id="I-B27K4V12-27-PROV-15" xy="3721, 3504, 3831, 3571">ου</word><word id="I-B27K4V12-27-PROV-16" xy="3844, 3503, 4301, 3570">κοπιαϲειϲ</word><word id="I-B27K4V12-27-PROV-17" xy="4315, 3503, 4339, 3570">·</word></line><line id="I-64-2v-2-43" xy="3107, 3565, 4517, 3629"><word id="I-B27K4V13-27-PROV-1" xy="3109, 3566, 3536, 3633">επιλαβου</word><word id="I-B27K4V13-27-PROV-2" xy="3532, 3569, 3776, 3636">εμηϲ</word><word id="I-B27K4V13-27-PROV-3" xy="3775, 3565, 4111, 3632">παιδιαϲ</word><word id="I-B27K4V13-27-PROV-4" xy="4106, 3565, 4250, 3632">μη</word><word id="I-B27K4V13-27-PROV-5" xy="4252, 3569, 4495, 3636">αφηϲ</word><word id="I-B27K4V13-27-PROV-6" xy="4498, 3565, 4524, 3632">·</word></line><line id="I-64-2v-2-44" xy="3103, 3630, 4245, 3694"><word id="I-B27K4V13-27-PROV-7" xy="3091, 3627, 3336, 3694">αλλα</word><word id="I-B27K4V13-27-PROV-8" xy="3331, 3630, 3751, 3697">φυλαξον</word><word id="I-B27K4V13-27-PROV-9" xy="3758, 3630, 4049, 3697">αυτην</word><word id="I-B27K4V13-27-PROV-10-1" xy="4051, 3630, 4271, 3697">ϲεαυ</word></line><line id="I-64-2v-2-45" xy="3309, 3690, 4056, 3754"><word id="I-B27K4V13-27-PROV-10-2" xy="3310, 3689, 3464, 3756">τω</word><word id="I-B27K4V13-27-PROV-11" xy="3455, 3689, 3476, 3756">.</word><word id="I-B27K4V13-27-PROV-12" xy="3466, 3685, 3596, 3752">ειϲ</word><word id="I-B27K4V13-27-PROV-13" xy="3591, 3686, 3867, 3753">ζωην</word><word id="I-B27K4V13-27-PROV-14" xy="3866, 3688, 4026, 3755">ϲου</word><word id="I-B27K4V13-27-PROV-15" xy="4037, 3682, 4075, 3749">·</word></line><line id="I-64-2v-2-46" xy="3105, 3749, 4238, 3813"><word id="I-B27K4V14-27-PROV-1" xy="3080, 3749, 3346, 3813">οδουϲ</word><word id="I-B27K4V14-27-PROV-2" xy="3346, 3749, 3657, 3813">αϲεβων</word><word id="I-B27K4V14-27-PROV-3" xy="3657, 3749, 3704, 3813">·</word><word id="I-B27K4V14-27-PROV-4" xy="3704, 3749, 3829, 3813">μη</word><word id="I-B27K4V14-27-PROV-5" xy="3829, 3749, 4188, 3813">επελθηϲ</word><word id="I-B27K4V14-27-PROV-6" xy="4188, 3749, 4260, 3813">·</word></line><line id="I-64-2v-2-47" xy="3110, 3811, 4556, 3875"><word id="I-B27K4V14-27-PROV-7" xy="3085, 3811, 3351, 3875">μηδε</word><word id="I-B27K4V14-27-PROV-8" xy="3355, 3811, 3768, 3878">ζηλωϲηϲ</word><word id="I-B27K4V14-27-PROV-9" xy="3770, 3813, 4021, 3880">οδουϲ</word><word id="I-B27K4V14-27-PROV-10" xy="4018, 3811, 4554, 3875">παρανομων</word><word id="I-B27K4V14-27-PROV-11" xy="4538, 3812, 4574, 3879">.</word></line><line id="I-64-2v-2-48" xy="3103, 3869, 4428, 3933"><word id="I-B27K4V15-27-PROV-1" xy="3078, 3869, 3212, 3933">εν</word><word id="I-B27K4V15-27-PROV-2" xy="3212, 3869, 3296, 3933">ω</word><word id="I-B27K4V15-27-PROV-3" xy="3305, 3872, 3417, 3939">αν</word><word id="I-B27K4V15-27-PROV-4" xy="3401, 3857, 3469, 3924">[...]</word><word id="I-B27K4V15-27-PROV-5" xy="3419, 3878, 4282, 3945">ϲτρατοπαιδευϲωϲιν</word><word id="I-B27K4V15-27-PROV-6" xy="4288, 3873, 4448, 3940">μη</word></line></col></page>
