

<page id="I-64-7r" xy="199, 230, 4264, 4802"><col id="I-64-7r-1" xy="431, 903, 1884, 3834"><line id="I-64-7r-1-1" xy="431, 880, 1760, 944"><word id="I-B27K13V13-27-PROV-28" xy="406, 880, 559, 944">και</word><word id="I-B27K13V13-27-PROV-29" xy="559, 880, 1263, 944">κατευθυνθηϲεται</word><word id="I-B27K13V13-27-PROV-30" xy="1263, 880, 1326, 944">η</word><word id="I-B27K13V13-27-PROV-31" xy="1326, 880, 1527, 944">οδοϲ</word><word id="I-B27K13V13-27-PROV-32" xy="1527, 880, 1782, 944">αυτου</word></line><line id="I-64-7r-1-2" xy="430, 939, 1500, 1003"><word id="I-B27K13V14-27-PROV-1" xy="425, 939, 726, 1006">νομοϲ</word><word id="I-B27K13V14-27-PROV-2" xy="728, 938, 993, 1005">ϲοφου</word><word id="I-B27K13V14-27-PROV-3" xy="991, 938, 1009, 1005">·</word><word id="I-B27K13V14-27-PROV-4" xy="1007, 939, 1248, 1006">πηγη</word><word id="I-B27K13V14-27-PROV-5" xy="1252, 939, 1523, 1003">ζωηϲ</word></line><line id="I-64-7r-1-3" xy="418, 1000, 1691, 1064"><word id="I-B27K13V14-27-PROV-6" xy="393, 1000, 470, 1064">ο</word><word id="I-B27K13V14-27-PROV-7" xy="470, 1000, 576, 1064">δε</word><word id="I-B27K13V14-27-PROV-8" xy="572, 1000, 833, 1067">ανουϲ</word><word id="I-B27K13V14-27-PROV-9" xy="831, 999, 848, 1066">·</word><word id="I-B27K13V14-27-PROV-10" xy="848, 1000, 1016, 1067">ϋπο</word><word id="I-B27K13V14-27-PROV-11" xy="1028, 998, 1370, 1065">παγιδοϲ</word><word id="I-B27K13V14-27-PROV-12" xy="1367, 999, 1695, 1066">θανιται</word></line><line id="I-64-7r-1-4" xy="419, 1064, 1607, 1128"><word id="I-B27K13V15-27-PROV-1" xy="408, 1064, 747, 1131">ϲυνεϲιϲ</word><word id="I-B27K13V15-27-PROV-2" xy="744, 1063, 1002, 1130">αγαθη</word><word id="I-B27K13V15-27-PROV-3" xy="993, 1065, 1011, 1132">·</word><word id="I-B27K13V15-27-PROV-4" xy="1011, 1064, 1366, 1131">διδωϲιν</word><word id="I-B27K13V15-27-PROV-5" xy="1367, 1063, 1619, 1130">χαριν</word></line><line id="I-64-7r-1-5" xy="405, 1123, 1671, 1187"><word id="I-B27K13V15-27-PROV-6" xy="399, 1123, 501, 1190">το</word><word id="I-B27K13V15-27-PROV-7" xy="508, 1124, 606, 1191">δε</word><word id="I-B27K13V15-27-PROV-8" xy="604, 1123, 944, 1190">γνωναι</word><word id="I-B27K13V15-27-PROV-9" xy="959, 1123, 1265, 1190">νομον</word><word id="I-B27K13V15-27-PROV-10" xy="1262, 1123, 1285, 1190">·</word><word id="I-B27K13V15-27-PROV-11" xy="1283, 1123, 1685, 1190">διανοιαϲ</word></line><line id="I-64-7r-1-6" xy="650, 1187, 1235, 1251"><word id="I-B27K13V15-27-PROV-12" xy="645, 1187, 908, 1254">εϲτιν</word><word id="I-B27K13V15-27-PROV-13" xy="917, 1189, 1240, 1256">αγαθηϲ</word></line><line id="I-64-7r-1-7" xy="431, 1269, 1884, 1330"><word id="I-B27K13V15-27-PROV-14" xy="412, 1252, 597, 1316">οδοι</word><word id="I-B27K13V15-27-PROV-15" xy="594, 1254, 702, 1318">δε</word><word id="I-B27K13V15-27-PROV-16" xy="706, 1252, 1484, 1316">καταφρονουντων</word><word id="I-B27K13V15-27-PROV-17" xy="1487, 1247, 1510, 1311">.</word><word id="I-B27K13V15-27-PROV-18" xy="1506, 1239, 1602, 1303">εν</word><word id="I-B27K13V15-27-PROV-19" xy="1607, 1234, 1910, 1298">απωλια</word></line><line id="I-64-7r-1-8" xy="431, 1330, 1884, 1391"><word id="I-B27K13V16-27-PROV-1" xy="418, 1318, 590, 1382">παϲ</word><word id="I-B27K13V16-27-PROV-2" xy="592, 1316, 1061, 1380">πανουργοϲ</word><word id="I-B27K13V16-27-PROV-3" xy="1049, 1321, 1071, 1385">·</word><word id="I-B27K13V16-27-PROV-4" xy="1078, 1315, 1383, 1379">πραϲϲει</word><word id="I-B27K13V16-27-PROV-5" xy="1392, 1310, 1612, 1374">μετα</word><word id="I-B27K13V16-27-PROV-6" xy="1609, 1301, 1901, 1365">γνωϲεωϲ</word></line><line id="I-64-7r-1-9" xy="431, 1391, 1884, 1452"><word id="I-B27K13V16-27-PROV-7" xy="413, 1376, 464, 1440">ο</word><word id="I-B27K13V16-27-PROV-8" xy="467, 1376, 574, 1440">δε</word><word id="I-B27K13V16-27-PROV-9" xy="574, 1381, 875, 1445">αφρων</word><word id="I-B27K13V16-27-PROV-10" xy="876, 1384, 888, 1448">·</word><word id="I-B27K13V16-27-PROV-11" xy="901, 1377, 1357, 1441">εξεπεταϲε</word><word id="I-B27K13V16-27-PROV-12" xy="1360, 1373, 1649, 1437">εαυτου</word><word id="I-B27K13V16-27-PROV-13" xy="1647, 1366, 1881, 1430">κακια</word></line><line id="I-64-7r-1-10" xy="431, 1452, 1884, 1513"><word id="I-B27K13V17-27-PROV-1" xy="423, 1440, 794, 1504">βαϲιλευϲ</word><word id="I-B27K13V17-27-PROV-2" xy="798, 1439, 1094, 1503">θραϲυϲ</word><word id="I-B27K13V17-27-PROV-3" xy="1080, 1438, 1101, 1502">·</word><word id="I-B27K13V17-27-PROV-4" xy="1110, 1434, 1583, 1498">εμπεϲειται</word><word id="I-B27K13V17-27-PROV-5" xy="1593, 1431, 1712, 1495">ειϲ</word><word id="I-B27K13V17-27-PROV-6" xy="1712, 1426, 1921, 1490">κακα</word></line><line id="I-64-7r-1-11" xy="420, 1490, 1736, 1554"><word id="I-B27K13V17-27-PROV-7" xy="418, 1493, 768, 1560">αγγελοϲ</word><word id="I-B27K13V17-27-PROV-8" xy="768, 1490, 878, 1557">δε</word><word id="I-B27K13V17-27-PROV-9" xy="879, 1492, 1169, 1559">πιϲτοϲ</word><word id="I-B27K13V17-27-PROV-10" xy="1160, 1490, 1177, 1557">·</word><word id="I-B27K13V17-27-PROV-11" xy="1179, 1490, 1479, 1557">ρυϲεται</word><word id="I-B27K13V17-27-PROV-12" xy="1483, 1490, 1757, 1554">αυτον</word></line><line id="I-64-7r-1-12" xy="431, 1574, 1884, 1635"><word id="I-B27K13V18-27-PROV-1" xy="428, 1561, 762, 1625">πενιαν</word><word id="I-B27K13V18-27-PROV-2" xy="769, 1562, 901, 1626">και</word><word id="I-B27K13V18-27-PROV-3" xy="908, 1562, 1263, 1626">ατιμιαν</word><word id="I-B27K13V18-27-PROV-4" xy="1262, 1559, 1280, 1623">·</word><word id="I-B27K13V18-27-PROV-5" xy="1282, 1557, 1694, 1621">αφαιρειται</word><word id="I-B27K13V18-27-PROV-6" xy="1697, 1553, 1920, 1617">παιδια</word></line><line id="I-64-7r-1-13" xy="432, 1616, 1931, 1680"><word id="I-B27K13V18-27-PROV-7" xy="407, 1616, 479, 1680">ο</word><word id="I-B27K13V18-27-PROV-8" xy="479, 1616, 576, 1680">δε</word><word id="I-B27K13V18-27-PROV-9" xy="583, 1620, 1060, 1687">φυλαϲϲων</word><word id="I-B27K13V18-27-PROV-10" xy="1069, 1619, 1458, 1686">ελεγχουϲ</word><word id="I-B27K13V18-27-PROV-11" xy="1447, 1615, 1461, 1682">·</word><word id="I-B27K13V18-27-PROV-12" xy="1462, 1607, 1939, 1674">δοξαϲθηϲεται</word></line><line id="I-64-7r-1-14" xy="431, 1696, 1884, 1757"><word id="I-B27K13V19-27-PROV-1" xy="432, 1688, 882, 1752">επιθυμιαι</word><word id="I-B27K13V19-27-PROV-2" xy="891, 1683, 1268, 1747">ευϲεβων</word><word id="I-B27K13V19-27-PROV-3" xy="1262, 1686, 1279, 1750">·</word><word id="I-B27K13V19-27-PROV-4" xy="1277, 1674, 1661, 1738">ηδυνουϲι</word><word id="I-B27K13V19-27-PROV-5" xy="1672, 1673, 1895, 1737">ψυχη</word></line><line id="I-64-7r-1-15" xy="431, 1757, 1884, 1818"><word id="I-B27K13V19-27-PROV-6" xy="422, 1749, 621, 1813">εργα</word><word id="I-B27K13V19-27-PROV-7" xy="621, 1751, 721, 1815">δε</word><word id="I-B27K13V19-27-PROV-8" xy="724, 1752, 1064, 1816">αϲεβων</word><word id="I-B27K13V19-27-PROV-9" xy="1067, 1749, 1083, 1813">·</word><word id="I-B27K13V19-27-PROV-10" xy="1082, 1747, 1416, 1811">μακραν</word><word id="I-B27K13V19-27-PROV-11" xy="1431, 1741, 1587, 1805">απο</word><word id="I-B27K13V19-27-PROV-12" xy="1588, 1738, 1923, 1802">γνωϲεωϲ</word></line><line id="I-64-7r-1-16" xy="411, 1798, 1935, 1862"><word id="I-B27K13V20-27-PROV-1" xy="392, 1804, 429, 1871">[...]</word><word id="I-B27K13V20-27-PROV-2" xy="437, 1802, 1227, 1869">ϲυμπορευομενοϲ</word><word id="I-B27K13V20-27-PROV-3" xy="1227, 1801, 1534, 1868">ϲοφοιϲ</word><word id="I-B27K13V20-27-PROV-4" xy="1519, 1801, 1533, 1868">·</word><word id="I-B27K13V20-27-PROV-5" xy="1541, 1800, 1803, 1867">ϲοφοϲ</word><word id="I-B27K13V20-27-PROV-6" xy="1814, 1792, 1940, 1859">εϲη</word></line><line id="I-64-7r-1-17" xy="435, 1858, 1680, 1922"><word id="I-B27K13V20-27-PROV-7" xy="430, 1865, 481, 1932">ο</word><word id="I-B27K13V20-27-PROV-8" xy="483, 1860, 585, 1927">δε</word><word id="I-B27K13V20-27-PROV-9" xy="591, 1861, 1370, 1928">ϲυμπορευομενοϲ</word><word id="I-B27K13V20-27-PROV-10" xy="1376, 1858, 1670, 1925">αφρονι</word><word id="I-B27K13V20-27-PROV-11" xy="1669, 1859, 1682, 1926">.</word></line><line id="I-64-7r-1-18" xy="633, 1924, 1219, 1988"><word id="I-B27K13V20-27-PROV-12" xy="608, 1924, 1244, 1988">γνωϲθηϲεται</word></line><line id="I-64-7r-1-19" xy="417, 1979, 1828, 2043"><word id="I-B27K13V21-27-PROV-1" xy="423, 1979, 1047, 2046">αμαρτανονταϲ</word><word id="I-B27K13V21-27-PROV-2" xy="1033, 1982, 1054, 2049">·</word><word id="I-B27K13V21-27-PROV-3" xy="1061, 1979, 1618, 2046">καταδιωξεται</word><word id="I-B27K13V21-27-PROV-4" xy="1626, 1979, 1830, 2046">κακα</word></line><line id="I-64-7r-1-20" xy="431, 2063, 1884, 2124"><word id="I-B27K13V21-27-PROV-5" xy="408, 2049, 608, 2113">τουϲ</word><word id="I-B27K13V21-27-PROV-6" xy="609, 2047, 713, 2111">δε</word><word id="I-B27K13V21-27-PROV-7" xy="716, 2049, 1071, 2113">δικαιουϲ</word><word id="I-B27K13V21-27-PROV-8" xy="1064, 2051, 1085, 2115">·</word><word id="I-B27K13V21-27-PROV-9" xy="1083, 2044, 1650, 2108">καταλημψεται</word><word id="I-B27K13V21-27-PROV-10" xy="1655, 2036, 1898, 2100">αγαθα</word></line><line id="I-64-7r-1-21" xy="431, 2124, 1884, 2185"><word id="I-B27K13V22-27-PROV-1" xy="422, 2111, 718, 2175">αγαθοϲ</word><word id="I-B27K13V22-27-PROV-2" xy="721, 2112, 926, 2176">ανηρ</word><word id="I-B27K13V22-27-PROV-3" xy="920, 2108, 939, 2172">·</word><word id="I-B27K13V22-27-PROV-4" xy="938, 2103, 1551, 2167">κληρονομηϲει</word><word id="I-B27K13V22-27-PROV-5" xy="1567, 2095, 1765, 2159">ϋϊουϲ</word><word id="I-B27K13V22-27-PROV-6" xy="1761, 2087, 1914, 2151">ϋϊων</word></line><line id="I-64-7r-1-22" xy="426, 2166, 1599, 2230"><word id="I-B27K13V22-27-PROV-7" xy="428, 2162, 955, 2229">θηϲαυριζετε</word><word id="I-B27K13V22-27-PROV-8" xy="955, 2165, 1059, 2232">δε</word><word id="I-B27K13V22-27-PROV-9" xy="1057, 2163, 1389, 2230">δικαιοιϲ</word><word id="I-B27K13V22-27-PROV-10" xy="1386, 2163, 1404, 2230">·</word><word id="I-B27K13V22-27-PROV-11-1" xy="1401, 2158, 1605, 2225">πλου</word></line><line id="I-64-7r-1-23" xy="614, 2227, 1123, 2291"><word id="I-B27K13V22-27-PROV-11-2" xy="614, 2227, 786, 2294">τοϲ</word><word id="I-B27K13V22-27-PROV-12" xy="783, 2228, 1122, 2295">αϲεβων</word></line><line id="I-64-7r-1-24" xy="423, 2291, 1675, 2355"><word id="I-B27K13V23-27-PROV-1" xy="410, 2291, 734, 2358">δικαιοι</word><word id="I-B27K13V23-27-PROV-2" xy="730, 2288, 1231, 2355">ποιηϲουϲιν</word><word id="I-B27K13V23-27-PROV-3" xy="1229, 2291, 1333, 2358">εν</word><word id="I-B27K13V23-27-PROV-4" xy="1335, 2287, 1659, 2354">πλουτω</word><word id="I-B27K13V23-27-PROV-5" xy="1657, 2291, 1674, 2358">.</word></line><line id="I-64-7r-1-25" xy="653, 2343, 1115, 2407"><word id="I-B27K13V23-27-PROV-6" xy="628, 2343, 820, 2407">ετη</word><word id="I-B27K13V23-27-PROV-7" xy="823, 2346, 1118, 2413">πολλα</word></line><line id="I-64-7r-1-26" xy="424, 2403, 1784, 2467"><word id="I-B27K13V23-27-PROV-8" xy="419, 2403, 713, 2470">αδικοι</word><word id="I-B27K13V23-27-PROV-9" xy="716, 2403, 821, 2470">δε</word><word id="I-B27K13V23-27-PROV-10" xy="816, 2405, 834, 2472">·</word><word id="I-B27K13V23-27-PROV-11" xy="831, 2403, 1330, 2470">απολουνται</word><word id="I-B27K13V23-27-PROV-12" xy="1341, 2403, 1781, 2470">ϲυντομωϲ</word></line><line id="I-64-7r-1-27" xy="424, 2470, 1606, 2534"><word id="I-B27K13V24-27-PROV-1" xy="414, 2470, 542, 2537">οϲ</word><word id="I-B27K13V24-27-PROV-2" xy="541, 2468, 911, 2535">φειδεται</word><word id="I-B27K13V24-27-PROV-3" xy="915, 2470, 1078, 2537">τηϲ</word><word id="I-B27K13V24-27-PROV-4" xy="1083, 2470, 1504, 2537">βακτηριαϲ</word><word id="I-B27K13V24-27-PROV-5" xy="1497, 2468, 1514, 2535">·</word><word id="I-B27K13V24-27-PROV-6-1" xy="1515, 2468, 1600, 2535">μι</word></line><line id="I-64-7r-1-28" xy="638, 2525, 1363, 2589"><word id="I-B27K13V24-27-PROV-6-2" xy="613, 2525, 717, 2589">ϲι</word><word id="I-B27K13V24-27-PROV-7" xy="717, 2525, 883, 2589">τον</word><word id="I-B27K13V24-27-PROV-8" xy="891, 2523, 1104, 2590">ϋϊον</word><word id="I-B27K13V24-27-PROV-9" xy="1108, 2525, 1370, 2592">αυτου</word></line><line id="I-64-7r-1-29" xy="433, 2590, 1765, 2654"><word id="I-B27K13V24-27-PROV-10" xy="408, 2590, 485, 2654">ο</word><word id="I-B27K13V24-27-PROV-11" xy="485, 2590, 592, 2654">δε</word><word id="I-B27K13V24-27-PROV-12" xy="600, 2590, 963, 2657">αγαπων</word><word id="I-B27K13V24-27-PROV-13" xy="961, 2590, 980, 2657">.</word><word id="I-B27K13V24-27-PROV-14" xy="977, 2590, 1408, 2657">επιμελωϲ</word><word id="I-B27K13V24-27-PROV-15" xy="1405, 2590, 1803, 2654">παιδευει</word></line><line id="I-64-7r-1-30" xy="437, 2647, 1631, 2711"><word id="I-B27K13V25-27-PROV-1" xy="447, 2648, 785, 2715">δικαιοϲ</word><word id="I-B27K13V25-27-PROV-2" xy="782, 2649, 1085, 2716">εϲθων</word><word id="I-B27K13V25-27-PROV-3" xy="1074, 2648, 1092, 2715">·</word><word id="I-B27K13V25-27-PROV-4" xy="1090, 2647, 1465, 2714">εμπιπλα</word><word id="I-B27K13V25-27-PROV-5" xy="1457, 2645, 1644, 2712">την</word></line><line id="I-64-7r-1-31" xy="623, 2720, 1175, 2784"><word id="I-B27K13V25-27-PROV-6" xy="598, 2720, 926, 2784">ψυχην</word><word id="I-B27K13V25-27-PROV-7" xy="926, 2720, 1199, 2784">αυτου</word></line><line id="I-64-7r-1-32" xy="403, 2787, 1473, 2851"><word id="I-B27K13V25-27-PROV-8" xy="406, 2787, 684, 2854">ψυχαι</word><word id="I-B27K13V25-27-PROV-9" xy="686, 2787, 801, 2854">δε</word><word id="I-B27K13V25-27-PROV-10" xy="796, 2785, 1131, 2852">αϲεβων</word><word id="I-B27K13V25-27-PROV-11" xy="1133, 2783, 1474, 2850">ενδεειϲ</word></line><line id="I-64-7r-1-33" xy="431, 2856, 1887, 2920"><word id="I-B27K14V1-27-PROV-1" xy="438, 2855, 712, 2922">ϲοφαι</word><word id="I-B27K14V1-27-PROV-2" xy="712, 2848, 1117, 2915">γυναικεϲ</word><word id="I-B27K14V1-27-PROV-3" xy="1103, 2852, 1120, 2919">·</word><word id="I-B27K14V1-27-PROV-4" xy="1126, 2849, 1724, 2916">ωκοδομηϲαν</word><word id="I-B27K14V1-27-PROV-5" xy="1732, 2841, 1911, 2908">οικουϲ</word></line><line id="I-64-7r-1-34" xy="439, 2917, 1643, 2981"><word id="I-B27K14V1-27-PROV-6" xy="414, 2917, 505, 2981">η</word><word id="I-B27K14V1-27-PROV-7" xy="505, 2917, 614, 2981">δε</word><word id="I-B27K14V1-27-PROV-8" xy="614, 2917, 926, 2981">αφρων</word><word id="I-B27K14V1-27-PROV-9" xy="927, 2917, 941, 2984">·</word><word id="I-B27K14V1-27-PROV-10" xy="944, 2917, 1459, 2984">κατεϲκαψεν</word><word id="I-B27K14V1-27-PROV-11" xy="1463, 2917, 1647, 2984">ταιϲ</word></line><line id="I-64-7r-1-35" xy="632, 2980, 1194, 3044"><word id="I-B27K14V1-27-PROV-12" xy="607, 2980, 930, 3044">χερϲιν</word><word id="I-B27K14V1-27-PROV-13" xy="930, 2980, 1218, 3044">αυτηϲ</word></line><line id="I-64-7r-1-36" xy="447, 3030, 1951, 3094"><word id="I-B27K14V2-27-PROV-1" xy="433, 3036, 488, 3103">ο</word><word id="I-B27K14V2-27-PROV-2" xy="494, 3037, 1120, 3104">πορευομενοϲ</word><word id="I-B27K14V2-27-PROV-3" xy="1127, 3030, 1399, 3097">ορθωϲ</word><word id="I-B27K14V2-27-PROV-4" xy="1393, 3030, 1405, 3097">·</word><word id="I-B27K14V2-27-PROV-5" xy="1416, 3025, 1780, 3092">φοβειται</word><word id="I-B27K14V2-27-PROV-6" xy="1781, 3021, 1887, 3088">τον</word><word id="I-B27K14V2-27-PROV-7" xy="1885, 3012, 1974, 3079">κν</word></line><line id="I-64-7r-1-37" xy="431, 3099, 1739, 3163"><word id="I-B27K14V2-27-PROV-8" xy="419, 3103, 496, 3170">ο</word><word id="I-B27K14V2-27-PROV-9" xy="461, 3080, 558, 3134">[...]</word><word id="I-B27K14V2-27-PROV-10" xy="496, 3110, 966, 3177">ϲκολιαζων</word><word id="I-B27K14V2-27-PROV-11" xy="977, 3099, 1145, 3166">ταιϲ</word><word id="I-B27K14V2-27-PROV-12" xy="1147, 3098, 1374, 3165">οδοιϲ</word><word id="I-B27K14V2-27-PROV-13" xy="1375, 3099, 1613, 3166">αυτου</word><word id="I-B27K14V2-27-PROV-14" xy="1607, 3098, 1622, 3165">·</word><word id="I-B27K14V2-27-PROV-15-1" xy="1623, 3096, 1737, 3163">ατι</word></line><line id="I-64-7r-1-38" xy="650, 3161, 1172, 3225"><word id="I-B27K14V2-27-PROV-15-2" xy="625, 3161, 1197, 3225">μαϲθηϲεται</word></line><line id="I-64-7r-1-39" xy="431, 3223, 1884, 3284"><word id="I-B27K14V3-27-PROV-1" xy="417, 3228, 541, 3292">εκ</word><word id="I-B27K14V3-27-PROV-2" xy="537, 3227, 933, 3291">ϲτοματοϲ</word><word id="I-B27K14V3-27-PROV-3" xy="933, 3227, 1339, 3291">αφρονων</word><word id="I-B27K14V3-27-PROV-4" xy="1336, 3223, 1357, 3287">·</word><word id="I-B27K14V3-27-PROV-5" xy="1357, 3220, 1709, 3284">βακτηρια</word><word id="I-B27K14V3-27-PROV-6" xy="1702, 3218, 1915, 3282">υβρεωϲ</word></line><line id="I-64-7r-1-40" xy="415, 3282, 1730, 3346"><word id="I-B27K14V3-27-PROV-7" xy="402, 3286, 621, 3353">χιλη</word><word id="I-B27K14V3-27-PROV-8" xy="618, 3283, 727, 3350">δε</word><word id="I-B27K14V3-27-PROV-9" xy="726, 3286, 1046, 3353">ϲοφων</word><word id="I-B27K14V3-27-PROV-10" xy="1045, 3286, 1063, 3353">·</word><word id="I-B27K14V3-27-PROV-11" xy="1060, 3285, 1441, 3352">φυλαϲϲει</word><word id="I-B27K14V3-27-PROV-12" xy="1447, 3281, 1734, 3348">αυτουϲ</word></line><line id="I-64-7r-1-41" xy="430, 3339, 1696, 3403"><word id="I-B27K14V4-27-PROV-1" xy="405, 3339, 535, 3403">ου</word><word id="I-B27K14V4-27-PROV-2" xy="535, 3339, 672, 3403">μη</word><word id="I-B27K14V4-27-PROV-3" xy="672, 3339, 882, 3403">ειϲιν</word><word id="I-B27K14V4-27-PROV-4" xy="890, 3339, 1085, 3406">βοεϲ</word><word id="I-B27K14V4-27-PROV-5" xy="1084, 3340, 1100, 3407">.</word><word id="I-B27K14V4-27-PROV-6" xy="1095, 3341, 1382, 3408">φατναι</word><word id="I-B27K14V4-27-PROV-7" xy="1395, 3337, 1692, 3404">καθαραι</word></line><line id="I-64-7r-1-42" xy="431, 3406, 1884, 3467"><word id="I-B27K14V4-27-PROV-8" xy="419, 3406, 536, 3470">ου</word><word id="I-B27K14V4-27-PROV-9" xy="537, 3405, 639, 3469">δε</word><word id="I-B27K14V4-27-PROV-10" xy="642, 3407, 907, 3471">πολλα</word><word id="I-B27K14V4-27-PROV-11" xy="908, 3406, 1323, 3470">γενηματα</word><word id="I-B27K14V4-27-PROV-12" xy="1317, 3407, 1335, 3471">·</word><word id="I-B27K14V4-27-PROV-13" xy="1341, 3403, 1642, 3467">φανερα</word><word id="I-B27K14V4-27-PROV-14" xy="1643, 3393, 1811, 3457">βοοϲ</word><word id="I-B27K14V4-27-PROV-15" xy="1806, 3390, 1935, 3454">ϊϲχυϲ</word></line><line id="I-64-7r-1-43" xy="429, 3471, 1502, 3535"><word id="I-B27K14V5-27-PROV-1" xy="423, 3471, 738, 3538">μαρτυϲ</word><word id="I-B27K14V5-27-PROV-2" xy="739, 3470, 1026, 3537">πιϲτοϲ</word><word id="I-B27K14V5-27-PROV-3" xy="1015, 3471, 1033, 3538">·</word><word id="I-B27K14V5-27-PROV-4" xy="1030, 3471, 1132, 3535">ου</word><word id="I-B27K14V5-27-PROV-5" xy="1132, 3471, 1526, 3535">ψευδεται</word></line><line id="I-64-7r-1-44" xy="427, 3523, 1730, 3587"><word id="I-B27K14V5-27-PROV-6" xy="427, 3525, 720, 3592">εκκαει</word><word id="I-B27K14V5-27-PROV-7" xy="717, 3523, 823, 3587">δε</word><word id="I-B27K14V5-27-PROV-8" xy="822, 3525, 1096, 3592">ψευδη</word><word id="I-B27K14V5-27-PROV-9" xy="1098, 3523, 1111, 3590">·</word><word id="I-B27K14V5-27-PROV-10" xy="1113, 3525, 1418, 3592">μαρτυϲ</word><word id="I-B27K14V5-27-PROV-11" xy="1419, 3523, 1733, 3590">αδικοϲ</word></line><line id="I-64-7r-1-45" xy="427, 3588, 1783, 3652"><word id="I-B27K14V6-27-PROV-1" xy="418, 3588, 828, 3655">ζητηϲειϲ</word><word id="I-B27K14V6-27-PROV-2" xy="824, 3588, 1144, 3655">ϲοφιαν</word><word id="I-B27K14V6-27-PROV-3" xy="1146, 3587, 1355, 3654">παρα</word><word id="I-B27K14V6-27-PROV-4" xy="1349, 3580, 1638, 3647">κακοιϲ</word><word id="I-B27K14V6-27-PROV-5" xy="1629, 3577, 1646, 3644">·</word><word id="I-B27K14V6-27-PROV-6" xy="1646, 3574, 1782, 3641">και</word></line><line id="I-64-7r-1-46" xy="648, 3651, 1205, 3715"><word id="I-B27K14V6-27-PROV-7" xy="642, 3651, 835, 3718">ουχ</word><word id="I-B27K14V6-27-PROV-8" xy="830, 3650, 1206, 3717">ευρηϲειϲ</word></line><line id="I-64-7r-1-47" xy="431, 3713, 1835, 3777"><word id="I-B27K14V6-27-PROV-9" xy="430, 3712, 789, 3779">αιϲθηϲιϲ</word><word id="I-B27K14V6-27-PROV-10" xy="786, 3712, 887, 3779">δε</word><word id="I-B27K14V6-27-PROV-11" xy="884, 3713, 1078, 3780">παρα</word><word id="I-B27K14V6-27-PROV-12" xy="1077, 3709, 1507, 3776">φρονιμοιϲ</word><word id="I-B27K14V6-27-PROV-13" xy="1496, 3706, 1514, 3773">·</word><word id="I-B27K14V6-27-PROV-14" xy="1516, 3704, 1834, 3771">ευχερηϲ</word></line><line id="I-64-7r-1-48" xy="438, 3775, 1576, 3839"><word id="I-B27K14V7-27-PROV-1" xy="429, 3775, 710, 3842">παντα</word><word id="I-B27K14V7-27-PROV-2" xy="709, 3775, 1045, 3842">εναντια</word><word id="I-B27K14V7-27-PROV-3" xy="1044, 3775, 1063, 3842">·</word><word id="I-B27K14V7-27-PROV-4" xy="1060, 3775, 1286, 3839">ανδρι</word><word id="I-B27K14V7-27-PROV-5" xy="1286, 3775, 1599, 3839">αφρονι</word></line></col><col id="I-64-7r-2" xy="2173, 901, 3603, 3829"><line id="I-64-7r-2-1" xy="2173, 880, 3409, 944"><word id="I-B27K14V7-27-PROV-6" xy="2162, 880, 2368, 947">οπλα</word><word id="I-B27K14V7-27-PROV-7" xy="2365, 880, 2469, 947">δε</word><word id="I-B27K14V7-27-PROV-8" xy="2470, 880, 2919, 947">αιϲθηϲεωϲ</word><word id="I-B27K14V7-27-PROV-9" xy="2918, 876, 2935, 943">·</word><word id="I-B27K14V7-27-PROV-10" xy="2929, 874, 3162, 941">χειλη</word><word id="I-B27K14V7-27-PROV-11" xy="3173, 874, 3405, 941">ϲοφα</word></line><line id="I-64-7r-2-2" xy="2165, 939, 3482, 1003"><word id="I-B27K14V8-27-PROV-1" xy="2170, 939, 2433, 1006">ϲοφια</word><word id="I-B27K14V8-27-PROV-2" xy="2431, 939, 2938, 1006">πανουργων</word><word id="I-B27K14V8-27-PROV-3" xy="2937, 938, 2956, 1005">·</word><word id="I-B27K14V8-27-PROV-4" xy="2953, 928, 3480, 995">επιγνωϲεται</word></line><line id="I-64-7r-2-3" xy="2346, 995, 3025, 1059"><word id="I-B27K14V8-27-PROV-5" xy="2342, 1000, 2485, 1067">ταϲ</word><word id="I-B27K14V8-27-PROV-6" xy="2482, 995, 2741, 1062">οδουϲ</word><word id="I-B27K14V8-27-PROV-7" xy="2735, 995, 3048, 1062">αυτων</word></line><line id="I-64-7r-2-4" xy="2165, 1055, 3359, 1119"><word id="I-B27K14V8-27-PROV-8" xy="2140, 1055, 2409, 1119">ανοια</word><word id="I-B27K14V8-27-PROV-9" xy="2409, 1055, 2518, 1119">δε</word><word id="I-B27K14V8-27-PROV-10" xy="2516, 1055, 2948, 1122">αφρονων</word><word id="I-B27K14V8-27-PROV-11" xy="2943, 1055, 2965, 1122">.</word><word id="I-B27K14V8-27-PROV-12" xy="2958, 1055, 3074, 1122">εν</word><word id="I-B27K14V8-27-PROV-13" xy="3073, 1043, 3362, 1110">πλανη</word></line><line id="I-64-7r-2-5" xy="2172, 1117, 3418, 1181"><word id="I-B27K14V9-27-PROV-1" xy="2175, 1121, 2427, 1188">οικιαι</word><word id="I-B27K14V9-27-PROV-2" xy="2434, 1117, 2952, 1184">παρανομων</word><word id="I-B27K14V9-27-PROV-3" xy="2946, 1115, 2965, 1182">·</word><word id="I-B27K14V9-27-PROV-4" xy="2964, 1101, 3425, 1168">οφιληϲουϲι</word></line><line id="I-64-7r-2-6" xy="2360, 1185, 2851, 1249"><word id="I-B27K14V9-27-PROV-5" xy="2335, 1185, 2876, 1249">καθαριϲμον</word></line><line id="I-64-7r-2-7" xy="2168, 1243, 3154, 1307"><word id="I-B27K14V9-27-PROV-6" xy="2157, 1244, 2421, 1311">οικιαι</word><word id="I-B27K14V9-27-PROV-7" xy="2418, 1244, 2529, 1311">δε</word><word id="I-B27K14V9-27-PROV-8" xy="2526, 1242, 2893, 1309">δικαιων</word><word id="I-B27K14V9-27-PROV-9" xy="2895, 1232, 3158, 1299">δεκται</word></line><line id="I-64-7r-2-8" xy="2174, 1305, 3450, 1369"><word id="I-B27K14V10-27-PROV-1" xy="2174, 1305, 2436, 1372">καρδια</word><word id="I-B27K14V10-27-PROV-2" xy="2443, 1303, 2741, 1370">ανδροϲ</word><word id="I-B27K14V10-27-PROV-3" xy="2747, 1300, 3152, 1367">εϲθητικη</word><word id="I-B27K14V10-27-PROV-4" xy="3155, 1292, 3172, 1359">·</word><word id="I-B27K14V10-27-PROV-5" xy="3167, 1284, 3458, 1351">λυπηρα</word></line><line id="I-64-7r-2-9" xy="2338, 1365, 2830, 1429"><word id="I-B27K14V10-27-PROV-6" xy="2313, 1365, 2579, 1429">ψυχη</word><word id="I-B27K14V10-27-PROV-7" xy="2579, 1365, 2854, 1429">αυτου</word></line><line id="I-64-7r-2-10" xy="2168, 1428, 3271, 1492"><word id="I-B27K14V10-27-PROV-8" xy="2169, 1432, 2394, 1499">οταν</word><word id="I-B27K14V10-27-PROV-9" xy="2396, 1430, 2491, 1497">δε</word><word id="I-B27K14V10-27-PROV-10" xy="2490, 1430, 2989, 1497">ευφραινητε</word><word id="I-B27K14V10-27-PROV-11" xy="2977, 1431, 2996, 1498">.</word><word id="I-B27K14V10-27-PROV-12" xy="2983, 1428, 3144, 1492">ουκ</word><word id="I-B27K14V10-27-PROV-13-1" xy="3144, 1428, 3309, 1492">επι</word></line><line id="I-64-7r-2-11" xy="2356, 1494, 2907, 1558"><word id="I-B27K14V10-27-PROV-13-2" xy="2331, 1494, 2741, 1558">μιγνυται</word><word id="I-B27K14V10-27-PROV-14" xy="2741, 1494, 2931, 1558">ϋβρι</word></line><line id="I-64-7r-2-12" xy="2169, 1548, 3484, 1612"><word id="I-B27K14V11-27-PROV-1" xy="2170, 1550, 2432, 1617">οικιαι</word><word id="I-B27K14V11-27-PROV-2" xy="2435, 1551, 2772, 1618">αϲεβων</word><word id="I-B27K14V11-27-PROV-3" xy="2767, 1550, 2785, 1617">·</word><word id="I-B27K14V11-27-PROV-4" xy="2781, 1538, 3482, 1605">αφανιϲθηϲονται</word></line><line id="I-64-7r-2-13" xy="2177, 1609, 3610, 1673"><word id="I-B27K14V11-27-PROV-5" xy="2169, 1613, 2488, 1680">ϲκηναι</word><word id="I-B27K14V11-27-PROV-6" xy="2485, 1609, 2573, 1676">δε</word><word id="I-B27K14V11-27-PROV-7" xy="2576, 1605, 3224, 1672">κατορθουντων</word><word id="I-B27K14V11-27-PROV-8" xy="3225, 1598, 3242, 1665">·</word><word id="I-B27K14V11-27-PROV-9" xy="3237, 1581, 3659, 1648">ϲτηϲονται</word></line><line id="I-64-7r-2-14" xy="2172, 1673, 3402, 1737"><word id="I-B27K14V12-27-PROV-1" xy="2165, 1676, 2398, 1743">εϲτιν</word><word id="I-B27K14V12-27-PROV-2" xy="2409, 1673, 2610, 1740">οδοϲ</word><word id="I-B27K14V12-27-PROV-3" xy="2599, 1672, 2619, 1739">·</word><word id="I-B27K14V12-27-PROV-4" xy="2618, 1672, 2683, 1739">η</word><word id="I-B27K14V12-27-PROV-5" xy="2679, 1669, 2913, 1736">δοκει</word><word id="I-B27K14V12-27-PROV-6" xy="2916, 1665, 3118, 1732">παρα</word><word id="I-B27K14V12-27-PROV-7-1" xy="3118, 1655, 3405, 1722">ανθρω</word></line><line id="I-64-7r-2-15" xy="2361, 1730, 2978, 1794"><word id="I-B27K14V12-27-PROV-7-2" xy="2356, 1738, 2557, 1805">ποιϲ</word><word id="I-B27K14V12-27-PROV-8" xy="2540, 1737, 2558, 1804">·</word><word id="I-B27K14V12-27-PROV-9" xy="2564, 1731, 2768, 1798">ορθη</word><word id="I-B27K14V12-27-PROV-10" xy="2770, 1728, 2992, 1795">ειναι</word></line><line id="I-64-7r-2-16" xy="2158, 1793, 3318, 1857"><word id="I-B27K14V12-27-PROV-11" xy="2145, 1793, 2255, 1860">τα</word><word id="I-B27K14V12-27-PROV-12" xy="2253, 1795, 2360, 1862">δε</word><word id="I-B27K14V12-27-PROV-13" xy="2354, 1795, 2758, 1862">τελευταια</word><word id="I-B27K14V12-27-PROV-14" xy="2759, 1792, 3010, 1859">αυτηϲ</word><word id="I-B27K14V12-27-PROV-15" xy="2995, 1794, 3011, 1861">·</word><word id="I-B27K14V12-27-PROV-16" xy="3014, 1788, 3321, 1855">ερχεται</word></line><line id="I-64-7r-2-17" xy="2357, 1856, 3129, 1920"><word id="I-B27K14V12-27-PROV-17" xy="2332, 1856, 2483, 1920">ειϲ</word><word id="I-B27K14V12-27-PROV-18" xy="2483, 1856, 2908, 1920">πυθμενα</word><word id="I-B27K14V12-27-PROV-19" xy="2920, 1847, 3130, 1914">αδου</word></line><line id="I-64-7r-2-18" xy="2166, 1911, 3421, 1975"><word id="I-B27K14V13-27-PROV-1" xy="2154, 1917, 2297, 1984">εν</word><word id="I-B27K14V13-27-PROV-2" xy="2302, 1914, 2832, 1981">ευφροϲυνη</word><word id="I-B27K14V13-27-PROV-3" xy="2832, 1911, 2848, 1978">·</word><word id="I-B27K14V13-27-PROV-4" xy="2851, 1910, 2961, 1977">ου</word><word id="I-B27K14V13-27-PROV-5-1" xy="2960, 1905, 3418, 1972">προϲμιγνυ</word></line><line id="I-64-7r-2-19" xy="2343, 1979, 2710, 2043"><word id="I-B27K14V13-27-PROV-5-2" xy="2341, 1981, 2486, 2048">ται</word><word id="I-B27K14V13-27-PROV-6" xy="2479, 1984, 2711, 2051">λυπη</word></line><line id="I-64-7r-2-20" xy="2173, 2040, 3603, 2101"><word id="I-B27K14V13-27-PROV-7" xy="2150, 2034, 2598, 2098">τελευταια</word><word id="I-B27K14V13-27-PROV-8" xy="2598, 2034, 2702, 2098">δε</word><word id="I-B27K14V13-27-PROV-9" xy="2711, 2036, 2901, 2100">χαρα</word><word id="I-B27K14V13-27-PROV-10" xy="2895, 2030, 2915, 2094">·</word><word id="I-B27K14V13-27-PROV-11" xy="2916, 2032, 3039, 2096">ειϲ</word><word id="I-B27K14V13-27-PROV-12" xy="3039, 2024, 3380, 2088">πενθοϲ</word><word id="I-B27K14V13-27-PROV-13" xy="3380, 2014, 3639, 2078">ερχεται</word></line><line id="I-64-7r-2-21" xy="2164, 2091, 3329, 2155"><word id="I-B27K14V14-27-PROV-1" xy="2152, 2096, 2351, 2163">των</word><word id="I-B27K14V14-27-PROV-2" xy="2356, 2093, 2649, 2160">εαυτου</word><word id="I-B27K14V14-27-PROV-3" xy="2645, 2091, 2884, 2158">οδων</word><word id="I-B27K14V14-27-PROV-4" xy="2880, 2091, 2901, 2158">·</word><word id="I-B27K14V14-27-PROV-5-1" xy="2899, 2088, 3331, 2155">πληϲθηϲε</word></line><line id="I-64-7r-2-22" xy="2352, 2157, 3074, 2221"><word id="I-B27K14V14-27-PROV-5-2" xy="2342, 2161, 2484, 2228">ται</word><word id="I-B27K14V14-27-PROV-6" xy="2486, 2160, 3077, 2227">θραϲυκαρδιοϲ</word></line><line id="I-64-7r-2-23" xy="2173, 2223, 3603, 2284"><word id="I-B27K14V14-27-PROV-7" xy="2178, 2225, 2356, 2289">απο</word><word id="I-B27K14V14-27-PROV-8" xy="2353, 2223, 2467, 2284">δε</word><word id="I-B27K14V14-27-PROV-9" xy="2467, 2223, 2659, 2284">των</word><word id="I-B27K14V14-27-PROV-10" xy="2671, 2221, 3331, 2285">διανοηματων</word><word id="I-B27K14V14-27-PROV-11" xy="3335, 2209, 3591, 2273">αυτου</word><word id="I-B27K14V14-27-PROV-12" xy="3581, 2211, 3601, 2275">·</word></line><line id="I-64-7r-2-24" xy="2367, 2280, 2919, 2344"><word id="I-B27K14V14-27-PROV-13" xy="2342, 2280, 2597, 2344">ανηρ</word><word id="I-B27K14V14-27-PROV-14" xy="2597, 2280, 2943, 2344">αγαθοϲ</word></line><line id="I-64-7r-2-25" xy="2175, 2338, 3345, 2402"><word id="I-B27K14V15-27-PROV-1" xy="2179, 2347, 2496, 2414">ακακοϲ</word><word id="I-B27K14V15-27-PROV-2" xy="2484, 2342, 2503, 2409">·</word><word id="I-B27K14V15-27-PROV-3" xy="2507, 2339, 2852, 2406">πιϲτευει</word><word id="I-B27K14V15-27-PROV-4" xy="2866, 2339, 3123, 2406">παντι</word><word id="I-B27K14V15-27-PROV-5" xy="3122, 2334, 3346, 2401">λογω</word></line><line id="I-64-7r-2-26" xy="2187, 2388, 3637, 2452"><word id="I-B27K14V15-27-PROV-6" xy="2187, 2399, 2680, 2466">πανουργοϲ</word><word id="I-B27K14V15-27-PROV-7" xy="2686, 2396, 2776, 2463">δε</word><word id="I-B27K14V15-27-PROV-8" xy="2766, 2397, 2787, 2464">.</word><word id="I-B27K14V15-27-PROV-9" xy="2786, 2393, 3099, 2460">ερχεται</word><word id="I-B27K14V15-27-PROV-10" xy="3113, 2388, 3236, 2455">ειϲ</word><word id="I-B27K14V15-27-PROV-11" xy="3240, 2378, 3698, 2445">μετανοιαν</word></line><line id="I-64-7r-2-27" xy="2182, 2448, 3685, 2512"><word id="I-B27K14V16-27-PROV-1" xy="2181, 2460, 2467, 2527">ϲοφοϲ</word><word id="I-B27K14V16-27-PROV-2" xy="2475, 2458, 2890, 2525">φοβηθειϲ</word><word id="I-B27K14V16-27-PROV-3" xy="2876, 2456, 2893, 2523">·</word><word id="I-B27K14V16-27-PROV-4" xy="2897, 2448, 3356, 2515">εξεκλινεν</word><word id="I-B27K14V16-27-PROV-5" xy="3371, 2439, 3531, 2506">απο</word><word id="I-B27K14V16-27-PROV-6" xy="3529, 2431, 3720, 2498">κακου</word></line><line id="I-64-7r-2-28" xy="2177, 2518, 3578, 2582"><word id="I-B27K14V16-27-PROV-7" xy="2152, 2518, 2231, 2582">ο</word><word id="I-B27K14V16-27-PROV-8" xy="2231, 2518, 2342, 2582">δε</word><word id="I-B27K14V16-27-PROV-9" xy="2342, 2518, 2660, 2582">αφρων</word><word id="I-B27K14V16-27-PROV-10" xy="2660, 2518, 2775, 2582">εν</word><word id="I-B27K14V16-27-PROV-11" xy="2789, 2519, 3082, 2586">εαυτω</word><word id="I-B27K14V16-27-PROV-12" xy="3087, 2513, 3556, 2580">πεποιθωϲ</word><word id="I-B27K14V16-27-PROV-13" xy="3558, 2509, 3579, 2576">·</word></line><line id="I-64-7r-2-29" xy="2379, 2580, 3101, 2644"><word id="I-B27K14V16-27-PROV-14" xy="2363, 2584, 2773, 2651">μιγνυται</word><word id="I-B27K14V16-27-PROV-15" xy="2775, 2578, 3103, 2645">ανομω</word></line><line id="I-64-7r-2-30" xy="2180, 2646, 3567, 2710"><word id="I-B27K14V17-27-PROV-1" xy="2159, 2653, 2620, 2720">οξυθυμοϲ</word><word id="I-B27K14V17-27-PROV-2" xy="2603, 2651, 2622, 2718">·</word><word id="I-B27K14V17-27-PROV-3" xy="2616, 2648, 2947, 2715">πραϲϲει</word><word id="I-B27K14V17-27-PROV-4" xy="2949, 2645, 3174, 2712">μετα</word><word id="I-B27K14V17-27-PROV-5" xy="3174, 2641, 3568, 2708">αβουλιαϲ</word></line><line id="I-64-7r-2-31" xy="2173, 2711, 3603, 2772"><word id="I-B27K14V17-27-PROV-6" xy="2158, 2721, 2400, 2785">ανηρ</word><word id="I-B27K14V17-27-PROV-7" xy="2396, 2716, 2504, 2780">δε</word><word id="I-B27K14V17-27-PROV-8" xy="2502, 2717, 2964, 2781">φρονιμοϲ</word><word id="I-B27K14V17-27-PROV-9" xy="2945, 2711, 2967, 2775">·</word><word id="I-B27K14V17-27-PROV-10" xy="2971, 2711, 3250, 2775">πολλα</word><word id="I-B27K14V17-27-PROV-11" xy="3245, 2702, 3610, 2766">ϋποφερει</word></line><line id="I-64-7r-2-32" xy="2179, 2779, 3388, 2843"><word id="I-B27K14V18-27-PROV-1" xy="2176, 2781, 2694, 2848">μεριουνται</word><word id="I-B27K14V18-27-PROV-2" xy="2695, 2779, 3093, 2846">αφρονεϲ</word><word id="I-B27K14V18-27-PROV-3" xy="3088, 2770, 3388, 2837">κακιαν</word></line><line id="I-64-7r-2-33" xy="2178, 2844, 3364, 2908"><word id="I-B27K14V18-27-PROV-4" xy="2164, 2847, 2268, 2914">οι</word><word id="I-B27K14V18-27-PROV-5" xy="2268, 2844, 2377, 2911">δε</word><word id="I-B27K14V18-27-PROV-6" xy="2372, 2849, 2825, 2916">πανουργοι</word><word id="I-B27K14V18-27-PROV-7" xy="2825, 2848, 2844, 2915">·</word><word id="I-B27K14V18-27-PROV-8" xy="2849, 2840, 3358, 2907">κρατηϲουϲιν</word></line><line id="I-64-7r-2-34" xy="2369, 2911, 2879, 2975"><word id="I-B27K14V18-27-PROV-9" xy="2344, 2911, 2904, 2975">αιϲθηϲεωϲ</word></line><line id="I-64-7r-2-35" xy="2184, 2964, 3606, 3028"><word id="I-B27K14V19-27-PROV-1" xy="2184, 2969, 2799, 3036">ολιϲθηϲουϲιν</word><word id="I-B27K14V19-27-PROV-2" xy="2804, 2968, 3038, 3035">κακοι</word><word id="I-B27K14V19-27-PROV-3" xy="3030, 2964, 3046, 3031">.</word><word id="I-B27K14V19-27-PROV-4" xy="3045, 2959, 3358, 3026">εναντι</word><word id="I-B27K14V19-27-PROV-5" xy="3362, 2951, 3623, 3018">αγαθω</word></line><line id="I-64-7r-2-36" xy="2190, 3029, 3440, 3093"><word id="I-B27K14V19-27-PROV-6" xy="2165, 3029, 2328, 3093">και</word><word id="I-B27K14V19-27-PROV-7" xy="2328, 3029, 2648, 3093">αϲεβειϲ</word><word id="I-B27K14V19-27-PROV-8" xy="2648, 3029, 3324, 3093">θεραπευϲουϲιν</word><word id="I-B27K14V19-27-PROV-9" xy="3322, 3026, 3340, 3093">.</word><word id="I-B27K14V19-27-PROV-10-1" xy="3340, 3020, 3446, 3087">θυ</word></line><line id="I-64-7r-2-37" xy="2383, 3094, 2878, 3158"><word id="I-B27K14V19-27-PROV-10-2" xy="2386, 3094, 2516, 3161">ραϲ</word><word id="I-B27K14V19-27-PROV-11" xy="2516, 3093, 2879, 3160">δικαιων</word></line><line id="I-64-7r-2-38" xy="2173, 3157, 3606, 3221"><word id="I-B27K14V20-27-PROV-1" xy="2159, 3157, 2404, 3224">φιλοι</word><word id="I-B27K14V20-27-PROV-2" xy="2401, 3157, 2419, 3224">·</word><word id="I-B27K14V20-27-PROV-3" xy="2419, 3153, 2938, 3220">μιϲηϲουϲιν</word><word id="I-B27K14V20-27-PROV-4" xy="2940, 3147, 3249, 3214">φιλουϲ</word><word id="I-B27K14V20-27-PROV-5" xy="3250, 3137, 3614, 3204">πτωχουϲ</word></line><line id="I-64-7r-2-39" xy="2166, 3212, 3306, 3276"><word id="I-B27K14V20-27-PROV-6" xy="2167, 3212, 2395, 3279">φιλοι</word><word id="I-B27K14V20-27-PROV-7" xy="2402, 3213, 2512, 3280">δε</word><word id="I-B27K14V20-27-PROV-8" xy="2508, 3212, 2982, 3279">πλουϲιων</word><word id="I-B27K14V20-27-PROV-9" xy="2973, 3209, 2991, 3276">.</word><word id="I-B27K14V20-27-PROV-10" xy="2989, 3205, 3306, 3272">πολλοι</word></line><line id="I-64-7r-2-40" xy="2180, 3271, 3557, 3335"><word id="I-B27K14V21-27-PROV-1" xy="2182, 3280, 2240, 3347">ο</word><word id="I-B27K14V21-27-PROV-2" xy="2247, 3275, 2698, 3342">ατιμαζων</word><word id="I-B27K14V21-27-PROV-3" xy="2706, 3274, 3090, 3341">πενηταϲ</word><word id="I-B27K14V21-27-PROV-4" xy="3077, 3271, 3095, 3338">·</word><word id="I-B27K14V21-27-PROV-5" xy="3104, 3261, 3560, 3328">αμαρτανι</word></line><line id="I-64-7r-2-41" xy="2178, 3325, 3500, 3389"><word id="I-B27K14V21-27-PROV-6" xy="2179, 3332, 2476, 3399">ελεων</word><word id="I-B27K14V21-27-PROV-7" xy="2470, 3334, 2585, 3401">δε</word><word id="I-B27K14V21-27-PROV-8" xy="2581, 3336, 2952, 3403">πτωχουϲ</word><word id="I-B27K14V21-27-PROV-9" xy="2976, 3329, 3496, 3396">μακαριϲτοϲ</word></line><line id="I-64-7r-2-42" xy="2177, 3383, 3610, 3447"><word id="I-B27K14V22-27-PROV-1" xy="2179, 3390, 2796, 3457">πλανωμενοι</word><word id="I-B27K14V22-27-PROV-2" xy="2795, 3392, 2810, 3459">·</word><word id="I-B27K14V22-27-PROV-3" xy="2809, 3385, 3412, 3452">τεκταινουϲιν</word><word id="I-B27K14V22-27-PROV-4" xy="3413, 3368, 3619, 3435">κακα</word></line><line id="I-64-7r-2-43" xy="2182, 3456, 3354, 3520"><word id="I-B27K14V22-27-PROV-5" xy="2174, 3454, 2466, 3521">ελεον</word><word id="I-B27K14V22-27-PROV-6" xy="2468, 3452, 2568, 3519">δε</word><word id="I-B27K14V22-27-PROV-7" xy="2567, 3452, 2703, 3519">και</word><word id="I-B27K14V22-27-PROV-8" xy="2705, 3454, 3078, 3521">αληθιαν</word><word id="I-B27K14V22-27-PROV-9" xy="3077, 3454, 3097, 3521">·</word><word id="I-B27K14V22-27-PROV-10-1" xy="3095, 3446, 3353, 3513">τεκται</word></line><line id="I-64-7r-2-44" xy="2383, 3517, 2986, 3581"><word id="I-B27K14V22-27-PROV-10-2" xy="2370, 3517, 2705, 3584">νουϲιν</word><word id="I-B27K14V22-27-PROV-11" xy="2703, 3517, 2985, 3584">αγαθοι</word></line><line id="I-64-7r-2-45" xy="2180, 3583, 3502, 3647"><word id="I-B27K14V22-27-PROV-12" xy="2155, 3583, 2350, 3647">ουκ</word><word id="I-B27K14V22-27-PROV-13" xy="2350, 3583, 2814, 3647">επιϲτανται</word><word id="I-B27K14V22-27-PROV-14" xy="2824, 3575, 3074, 3642">ελεον</word><word id="I-B27K14V22-27-PROV-15" xy="3085, 3569, 3205, 3636">και</word><word id="I-B27K14V22-27-PROV-16" xy="3211, 3566, 3482, 3633">πιϲτιν</word><word id="I-B27K14V22-27-PROV-17" xy="3482, 3567, 3500, 3634">.</word></line><line id="I-64-7r-2-46" xy="2356, 3641, 3108, 3705"><word id="I-B27K14V22-27-PROV-18" xy="2365, 3639, 2807, 3706">τεκτονεϲ</word><word id="I-B27K14V22-27-PROV-19" xy="2806, 3633, 3115, 3700">κακων</word></line><line id="I-64-7r-2-47" xy="2193, 3708, 3387, 3772"><word id="I-B27K14V22-27-PROV-20" xy="2191, 3708, 2777, 3775">ελεημοϲυναι</word><word id="I-B27K14V22-27-PROV-21" xy="2771, 3702, 2879, 3769">δε</word><word id="I-B27K14V22-27-PROV-22" xy="2877, 3697, 3010, 3764">και</word><word id="I-B27K14V22-27-PROV-23" xy="3015, 3693, 3267, 3760">πιϲτιϲ</word><word id="I-B27K14V22-27-PROV-24" xy="3255, 3690, 3272, 3757">·</word><word id="I-B27K14V22-27-PROV-25-1" xy="3271, 3684, 3390, 3751">πα</word></line><line id="I-64-7r-2-48" xy="2387, 3776, 3159, 3840"><word id="I-B27K14V22-27-PROV-25-2" xy="2362, 3776, 2478, 3840">ρα</word><word id="I-B27K14V22-27-PROV-26" xy="2483, 3768, 2840, 3835">τεκτοϲιν</word><word id="I-B27K14V22-27-PROV-27" xy="2847, 3753, 3165, 3820">αγαθοιϲ</word></line></col></page>
